Workbook

Sheet README
A1: MediLens — Kế hoạch sprint dài hạn 52 tuần / 26 sprint (VI/EN)
A2: Long-term sprint plan: 7 phase · 26 sprint × 10 ngày làm việc · 260 việc theo ngày · 14 cổng chất lượng
A4: Mục đích / Purpose
A5: File này chia toàn bộ dự án MediLens thành từng sprint và từng ngày làm việc. Mỗi ngày có một việc chính, role (mũ) đang đội, skill nên gọi cho agent, đầu ra và tiêu chí xong. This workbook breaks the project into sprints and working days; each day names the role, the agent skill to call, the deliverable and the definition of done.
A6: Tài liệu dự án đầy đủ (mục 22–29 giải thích vì sao có các việc này): https://claude.ai/code/artifact/364d9184-4a53-4093-bd32-f1a068f6ba92
A8: Cách dùng / How to use
A9: 1. Sheet Settings: nhập Ngày bắt đầu (ô vàng). Toàn bộ ngày trong Daily Plan, Sprints, Gates, Gantt tự tính lại bằng WORKDAY, bỏ qua cuối tuần và ngày trong sheet Holidays.
A10: 2. Sheet Daily Plan: mỗi ngày cập nhật Trạng thái (Chưa làm / Đang làm / Xong / Trễ / Bỏ), Giờ thực tế và Ghi chú — chỉ 3 cột này là ô nhập (nền vàng).
A11: 3. Sheet Dashboard: xem sprint hiện tại, việc hôm nay, cổng kế tiếp, % hoàn thành so với tiến độ kỳ vọng.
A12: 4. Cuối mỗi sprint (ngày 10): Review + Retro, cập nhật Sprints và Gates (Trạng thái cổng).
A13: 5. Muốn đổi kế hoạch gốc (baseline)? Ghi vào Change Log trước rồi mới sửa Daily Plan — giống quy trình Change Request ở dự án lớn.
A14: 6. Gọi agent: lấy tên trong cột Skill (ví dụ medilens-backend-engineer) để agent dùng đúng skill của role đó; với việc nhiều role, gọi medilens-orchestrator.
... A32: Tết 2027: CafeF — Bộ Nội vụ thông báo lịch nghỉ Tết Nguyên đán Đinh Mùi 2027 (cafef.vn). 24/11: FPT Shop tóm tắt Nghị quyết 28/2026/QH16. Giỗ Tổ 16/04/2027: officeholidays.com. Các ngày còn lại: Bộ luật Lao động 2019.

Sheet Dashboard
A1: MediLens — Tổng quan tiến độ / Progress dashboard
A2: Tự cập nhật từ Daily Plan, Sprints, Gates. Không cần nhập gì ở sheet này.
A3: Chỉ số | B3: Metric | C3: Giá trị / Value | E3: Phase | F3: Bắt đầu | G3: Kết thúc | H3: Số việc | I3: Xong | J3: % xong | K3: Giờ KH | L3: Giờ TT
A4: Ngày bắt đầu | B4: Start date | C4: =Settings!$C$4 -> 46314 | E4: =Roadmap!A4 -> P0 · Khởi tạo & Discovery | F4: =Roadmap!G4 -> 46314 | G4: =Roadmap!H4 -> 46339 | H4: =Roadmap!M4 -> 20 | I4: =Roadmap!N4 -> 0 | J4: =Roadmap!O4 -> 0 | K4: =Roadmap!P4 -> 80 | L4: =Roadmap!Q4 -> 0
A5: Ngày kết thúc dự kiến | B5: Planned end date | C5: =Settings!$C$11 -> 46692 | E5: =Roadmap!A5 -> P1 · Foundation | F5: =Roadmap!G5 -> 46342 | G5: =Roadmap!H5 -> 46384 | H5: =Roadmap!M5 -> 30 | I5: =Roadmap!N5 -> 0 | J5: =Roadmap!O5 -> 0 | K5: =Roadmap!P5 -> 120 | L5: =Roadmap!Q5 -> 0
A6: Hôm nay | B6: Today | C6: =TODAY() -> 46311 | E6: =Roadmap!A6 -> P2 · Build MVP | F6: =Roadmap!G6 -> 46385 | G6: =Roadmap!H6 -> 46476 | H6: =Roadmap!M6 -> 60 | I6: =Roadmap!N6 -> 0 | J6: =Roadmap!O6 -> 0 | K6: =Roadmap!P6 -> 240 | L6: =Roadmap!Q6 -> 0
A7: Sprint hiện tại | B7: Current sprint | C7: =IF(TODAY()<Settings!$C$4,"Chưa bắt đầu",IF(TODAY()>Settings!$C$11,"Đã kết thúc",INDEX('Daily Plan'!$C$4:$C$263,MATCH(TODAY(),'Daily Plan'!$B$4:$B$263,1)))) -> Chưa bắt đầu | E7: =Roadmap!A7 -> P3 · Hardening | F7: =Roadmap!G7 -> 46477 | G7: =Roadmap!H7 -> 46520 | H7: =Roadmap!M7 -> 30 | I7: =Roadmap!N7 -> 0 | J7: =Roadmap!O7 -> 0 | K7: =Roadmap!P7 -> 120 | L7: =Roadmap!Q7 -> 0
A8: Việc hôm nay | B8: Today's task | C8: =IFERROR(INDEX('Daily Plan'!$I$4:$I$263,MATCH(TODAY(),'Daily Plan'!$B$4:$B$263,0)),"Không có việc theo lịch hôm nay") -> Không có việc theo lịch hôm nay | E8: =Roadmap!A8 -> P4 · Beta & Launch v1.0 | F8: =Roadmap!G8 -> 46521 | G8: =Roadmap!H8 -> 46548 | H8: =Roadmap!M8 -> 20 | I8: =Roadmap!N8 -> 0 | J8: =Roadmap!O8 -> 0 | K8: =Roadmap!P8 -> 80 | L8: =Roadmap!Q8 -> 0
A9: Cổng kế tiếp | B9: Next gate | C9: =IF(_xlfn.MINIFS(Gates!$E$4:$E$17,Gates!$E$4:$E$17,">="&TODAY())=0,"—",INDEX(Gates!$A$4:$A$17,MATCH(_xlfn.MINIFS(Gates!$E$4:$E$17,Gates!$E$4:$E$17,">="&TODAY()),Gates!$E$4:$E$17,0))) -> G0 | E9: =Roadmap!A9 -> P5 · Hypercare & v1.5 | F9: =Roadmap!G9 -> 46549 | G9: =Roadmap!H9 -> 46604 | H9: =Roadmap!M9 -> 40 | I9: =Roadmap!N9 -> 0 | J9: =Roadmap!O9 -> 0 | K9: =Roadmap!P9 -> 160 | L9: =Roadmap!Q9 -> 0
A10: Ngày cổng kế tiếp | B10: Next gate date | C10: =IF(_xlfn.MINIFS(Gates!$E$4:$E$17,Gates!$E$4:$E$17,">="&TODAY())=0,"—",_xlfn.MINIFS(Gates!$E$4:$E$17,Gates!$E$4:$E$17,">="&TODAY())) -> 46339 | E10: =Roadmap!A10 -> P6 · v2.0 — CT & giải phẫu cá nhân | F10: =Roadmap!G10 -> 46605 | G10: =Roadmap!H10 -> 46692 | H10: =Roadmap!M10 -> 60 | I10: =Roadmap!N10 -> 0 | J10: =Roadmap!O10 -> 0 | K10: =Roadmap!P10 -> 240 | L10: =Roadmap!Q10 -> 0
A11: Tổng số việc | B11: Total tasks | C11: =COUNTA('Daily Plan'!$I$4:$I$263) -> 260
A12: Việc đã xong | B12: Tasks done | C12: =COUNTIF('Daily Plan'!$P$4:$P$263,"Xong") -> 0
A13: % hoàn thành | B13: % complete | C13: =IFERROR(C12/C11,0) -> 0 | E13: Cổng | F13: Sprint | G13: Ngày dự kiến | H13: Trạng thái
A14: Tiến độ kỳ vọng tới hôm nay | B14: Expected progress to date | C14: =IFERROR(COUNTIF('Daily Plan'!$B$4:$B$263,"<"&TODAY())/C11,0) -> 0 | E14: =Gates!A4 -> G0 | F14: =Gates!D4 -> S02 | G14: =Gates!E4 -> 46339 | H14: =Gates!J4 -> Chưa đến
A15: Chênh lệch (âm = chậm) | B15: Variance (negative = behind) | C15: =C13-C14 -> 0 | E15: =Gates!A5 -> G0-R | F15: =Gates!D5 -> S02 | G15: =Gates!E5 -> 46339 | H15: =Gates!J5 -> Chưa đến
A16: Việc quá hạn | B16: Overdue tasks | C16: =COUNTIF('Daily Plan'!$Q$4:$Q$263,"Quá hạn") -> 0 | E16: =Gates!A6 -> G1 | F16: =Gates!D6 -> S05 | G16: =Gates!E6 -> 46384 | H16: =Gates!J6 -> Chưa đến
A17: Giờ kế hoạch | B17: Planned hours | C17: =SUM('Daily Plan'!$N$4:$N$263) -> 1040 | E17: =Gates!A7 -> G1-D | F17: =Gates!D7 -> S05 | G17: =Gates!E7 -> 46384 | H17: =Gates!J7 -> Chưa đến
A18: Giờ thực tế | B18: Actual hours | C18: =SUM('Daily Plan'!$O$4:$O$263) -> 0 | E18: =Gates!A8 -> G2 | F18: =Gates!D8 -> S11 | G18: =Gates!E8 -> 46476 | H18: =Gates!J8 -> Chưa đến
E19: =Gates!A9 -> G2-CS | F19: =Gates!D9 -> S13 | G19: =Gates!E9 -> 46505 | H19: =Gates!J9 -> Chưa đến
E20: =Gates!A10 -> G3 | F20: =Gates!D10 -> S14 | G20: =Gates!E10 -> 46520 | H20: =Gates!J10 -> Chưa đến
A21: Trạng thái | B21: Status | C21: Số việc | E21: =Gates!A11 -> G3-P | F21: =Gates!D11 -> S14 | G21: =Gates!E11 -> 46520 | H21: =Gates!J11 -> Chưa đến
A22: Chưa làm | B22: Not started | C22: =COUNTIF('Daily Plan'!$P$4:$P$263,A22) -> 260 | E22: =Gates!A12 -> G4 | F22: =Gates!D12 -> S16 | G22: =Gates!E12 -> 46548 | H22: =Gates!J12 -> Chưa đến
A23: Đang làm | B23: In progress | C23: =COUNTIF('Daily Plan'!$P$4:$P$263,A23) -> 0 | E23: =Gates!A13 -> G5-H | F23: =Gates!D13 -> S18 | G23: =Gates!E13 -> 46576 | H23: =Gates!J13 -> Chưa đến
A24: Xong | B24: Done | C24: =COUNTIF('Daily Plan'!$P$4:$P$263,A24) -> 0 | E24: =Gates!A14 -> G5 | F24: =Gates!D14 -> S20 | G24: =Gates!E14 -> 46604 | H24: =Gates!J14 -> Chưa đến
A25: Trễ | B25: Late | C25: =COUNTIF('Daily Plan'!$P$4:$P$263,A25) -> 0 | E25: =Gates!A15 -> G0-R (CT) | F25: =Gates!D15 -> S21 | G25: =Gates!E15 -> 46618 | H25: =Gates!J15 -> Chưa đến
A26: Bỏ | B26: Dropped | C26: =COUNTIF('Daily Plan'!$P$4:$P$263,A26) -> 0 | E26: =Gates!A16 -> G1-D (lần 2) | F26: =Gates!D16 -> S22 | G26: =Gates!E16 -> 46636 | H26: =Gates!J16 -> Chưa đến
E27: =Gates!A17 -> G6 | F27: =Gates!D17 -> S26 | G27: =Gates!E17 -> 46692 | H27: =Gates!J17 -> Chưa đến

Sheet Settings
A1: Cài đặt / Settings
A2: Chỉ sửa ô nền vàng. Edit yellow cells only.
A3: Tham số | B3: Parameter | C3: Giá trị / Value | D3: Ghi chú / Note
A4: Ngày bắt đầu Sprint 1 | B4: Sprint 1 start date | C4: 46314 | D4: Nhập một ngày thứ Hai. Mặc định 19/10/2026 (thứ Hai sau ngày lập kế hoạch 16/10/2026).
A5: Số giờ mỗi ngày làm việc | B5: Hours per working day | C5: 4 | D5: 20 giờ/tuần part-time theo mục 1 của tài liệu (5 ngày × 4 giờ).
A6: Số ngày làm việc mỗi tuần | B6: Working days per week | C6: 5 | D6: Thứ Hai–Thứ Sáu; WORKDAY bỏ qua cuối tuần và ngày trong Holidays.
A7: Số giờ mỗi tuần | B7: Hours per week | C7: =C5*C6 -> 20 | D7: Tính từ 2 ô trên.
A8: Số ngày mỗi sprint | B8: Days per sprint | C8: 10 | D8: Sprint 2 tuần.
A9: Tổng số sprint | B9: Total sprints | C9: =COUNTA(Sprints!$A$4:$A$29) -> 26
A10: Tổng số ngày làm việc | B10: Total working days | C10: =COUNT('Daily Plan'!$A$4:$A$263) -> 260
A11: Ngày kết thúc dự kiến | B11: Planned end date | C11: =MAX('Daily Plan'!$B$4:$B$263) -> 46692 | D11: Thay đổi khi đổi ngày bắt đầu hoặc thêm ngày nghỉ.
A12: Tổng giờ kế hoạch | B12: Total planned hours | C12: =SUM('Daily Plan'!$N$4:$N$263) -> 1040

Sheet Roadmap
A1: Lộ trình 7 phase / Roadmap
A2: Thay cho lộ trình 32 tuần ở mục 5 của tài liệu: v1.0 vẫn ra mắt ở tuần 32, sau đó v1.5 (tuần 33–40) và v2.0 (tuần 41–52).
A3: Phase | B3: Tên (VI) | C3: Name (EN) | D3: Sprint từ | E3: Sprint đến | F3: Tuần KH | G3: Bắt đầu | H3: Kết thúc | I3: Mục tiêu (VI) | J3: Objective (EN) | K3: Cổng ra | L3: Phát hành | M3: Số việc | N3: Xong | O3: % xong | P3: Giờ KH | Q3: Giờ TT
A4: P0 · Khởi tạo & Discovery | B4: Khởi tạo & Discovery | C4: Initiation & Discovery | D4: S01 | E4: S02 | F4: 1–4 | G4: =INDEX(Sprints!$D$4:$D$29,MATCH(D4,Sprints!$A$4:$A$29,0)) -> 46314 | H4: =INDEX(Sprints!$E$4:$E$29,MATCH(E4,Sprints!$A$4:$A$29,0)) -> 46339 | I4: Charter, intended use, nghiên cứu người dùng, khóa phạm vi MVP, golden set v0, chọn OCR | J4: Charter, intended use, user research, MVP scope, golden set v0, OCR choice | K4: G0, G0-R | M4: =COUNTIF('Daily Plan'!$F$4:$F$263,A4) -> 20 | N4: =COUNTIFS('Daily Plan'!$F$4:$F$263,A4,'Daily Plan'!$P$4:$P$263,"Xong") -> 0 | O4: =IFERROR(N4/M4,0) -> 0 | P4: =SUMIFS('Daily Plan'!$N$4:$N$263,'Daily Plan'!$F$4:$F$263,A4) -> 80 | Q4: =SUMIFS('Daily Plan'!$O$4:$O$263,'Daily Plan'!$F$4:$F$263,A4) -> 0
A5: P1 · Foundation | B5: Foundation | C5: Foundation | D5: S03 | E5: S05 | F5: 5–10 | G5: =INDEX(Sprints!$D$4:$D$29,MATCH(D5,Sprints!$A$4:$A$29,0)) -> 46342 | H5: =INDEX(Sprints!$E$4:$E$29,MATCH(E5,Sprints!$A$4:$A$29,0)) -> 46384 | I5: Repo, CI/CD, landing zone AWS, data model, ranh giới PHI mức A, pipeline AI tối giản trên staging | J5: Repo, CI/CD, AWS landing zone, data model, level-A PHI boundary, minimal AI pipeline on staging | K5: G1, G1-D (lần 1) | M5: =COUNTIF('Daily Plan'!$F$4:$F$263,A5) -> 30 | N5: =COUNTIFS('Daily Plan'!$F$4:$F$263,A5,'Daily Plan'!$P$4:$P$263,"Xong") -> 0 | O5: =IFERROR(N5/M5,0) -> 0 | P5: =SUMIFS('Daily Plan'!$N$4:$N$263,'Daily Plan'!$F$4:$F$263,A5) -> 120 | Q5: =SUMIFS('Daily Plan'!$O$4:$O$263,'Daily Plan'!$F$4:$F$263,A5) -> 0
A6: P2 · Build MVP | B6: Build MVP | C6: Build MVP | D6: S06 | E6: S11 | F6: 11–22 | G6: =INDEX(Sprints!$D$4:$D$29,MATCH(D6,Sprints!$A$4:$A$29,0)) -> 46385 | H6: =INDEX(Sprints!$E$4:$E$29,MATCH(E6,Sprints!$A$4:$A$29,0)) -> 46476 | I6: Upload → OCR → trích xuất → review, viewer 2D/3D, 3 Unit, RAG có guardrail, timeline, chia sẻ, mô tả text | J6: Upload → OCR → extraction → review, 2D/3D viewer, 3 Units, guarded RAG, timeline, sharing, text input | K6: G2 | M6: =COUNTIF('Daily Plan'!$F$4:$F$263,A6) -> 60 | N6: =COUNTIFS('Daily Plan'!$F$4:$F$263,A6,'Daily Plan'!$P$4:$P$263,"Xong") -> 0 | O6: =IFERROR(N6/M6,0) -> 0 | P6: =SUMIFS('Daily Plan'!$N$4:$N$263,'Daily Plan'!$F$4:$F$263,A6) -> 240 | Q6: =SUMIFS('Daily Plan'!$O$4:$O$263,'Daily Plan'!$F$4:$F$263,A6) -> 0
A7: P3 · Hardening | B7: Hardening | C7: Hardening | D7: S12 | E7: S14 | F7: 23–28 | G7: =INDEX(Sprints!$D$4:$D$29,MATCH(D7,Sprints!$A$4:$A$29,0)) -> 46477 | H7: =INDEX(Sprints!$E$4:$E$29,MATCH(E7,Sprints!$A$4:$A$29,0)) -> 46520 | I7: Bảo mật mức B, hiệu năng, a11y, an toàn lâm sàng, pháp lý, pentest độc lập, prod sẵn sàng | J7: Level-B security, performance, a11y, clinical safety, regulatory, external pentest, prod ready | K7: G2-CS, G3, G3-P | M7: =COUNTIF('Daily Plan'!$F$4:$F$263,A7) -> 30 | N7: =COUNTIFS('Daily Plan'!$F$4:$F$263,A7,'Daily Plan'!$P$4:$P$263,"Xong") -> 0 | O7: =IFERROR(N7/M7,0) -> 0 | P7: =SUMIFS('Daily Plan'!$N$4:$N$263,'Daily Plan'!$F$4:$F$263,A7) -> 120 | Q7: =SUMIFS('Daily Plan'!$O$4:$O$263,'Daily Plan'!$F$4:$F$263,A7) -> 0
A8: P4 · Beta & Launch v1.0 | B8: Beta & Launch v1.0 | C8: Beta & Launch v1.0 | D8: S15 | E8: S16 | F8: 29–32 | G8: =INDEX(Sprints!$D$4:$D$29,MATCH(D8,Sprints!$A$4:$A$29,0)) -> 46521 | H8: =INDEX(Sprints!$E$4:$E$29,MATCH(E8,Sprints!$A$4:$A$29,0)) -> 46548 | I8: Beta kín 10–20 người, UAT, phát hành v1.0, bắt đầu hypercare | J8: Closed beta (10–20 users), UAT, v1.0 release, hypercare starts | K8: G4 | L8: v1.0 | M8: =COUNTIF('Daily Plan'!$F$4:$F$263,A8) -> 20 | N8: =COUNTIFS('Daily Plan'!$F$4:$F$263,A8,'Daily Plan'!$P$4:$P$263,"Xong") -> 0 | O8: =IFERROR(N8/M8,0) -> 0 | P8: =SUMIFS('Daily Plan'!$N$4:$N$263,'Daily Plan'!$F$4:$F$263,A8) -> 80 | Q8: =SUMIFS('Daily Plan'!$O$4:$O$263,'Daily Plan'!$F$4:$F$263,A8) -> 0
A9: P5 · Hypercare & v1.5 | B9: Hypercare & v1.5 | C9: Hypercare & v1.5 | D9: S17 | E9: S20 | F9: 33–40 | G9: =INDEX(Sprints!$D$4:$D$29,MATCH(D9,Sprints!$A$4:$A$29,0)) -> 46549 | H9: =INDEX(Sprints!$E$4:$E$29,MATCH(E9,Sprints!$A$4:$A$29,0)) -> 46604 | I9: Thoát hypercare, nhập bệnh án số (PDF/DOCX/FHIR), thư viện template giải phẫu, thêm 2 Unit, cascade đầy đủ, dữ liệu tầng 3–4 | J9: Exit hypercare, digital record import (PDF/DOCX/FHIR), anatomy template library, 2 more Units, full cascade, tier 3–4 data | K9: G5-H, G5 | L9: v1.5 | M9: =COUNTIF('Daily Plan'!$F$4:$F$263,A9) -> 40 | N9: =COUNTIFS('Daily Plan'!$F$4:$F$263,A9,'Daily Plan'!$P$4:$P$263,"Xong") -> 0 | O9: =IFERROR(N9/M9,0) -> 0 | P9: =SUMIFS('Daily Plan'!$N$4:$N$263,'Daily Plan'!$F$4:$F$263,A9) -> 160 | Q9: =SUMIFS('Daily Plan'!$O$4:$O$263,'Daily Plan'!$F$4:$F$263,A9) -> 0
A10: P6 · v2.0 — CT & giải phẫu cá nhân | B10: v2.0 — CT & giải phẫu cá nhân | C10: v2.0 — CT & patient-specific anatomy | D10: S21 | E10: S26 | F10: 41–52 | G10: =INDEX(Sprints!$D$4:$D$29,MATCH(D10,Sprints!$A$4:$A$29,0)) -> 46605 | H10: =INDEX(Sprints!$E$4:$E$29,MATCH(E10,Sprints!$A$4:$A$29,0)) -> 46692 | I10: Tái đánh giá pháp lý cho CT, DICOM an toàn, segmentation, mesh cá nhân, registration, distillation, FHIR export, đóng năm 1 | J10: Regulatory re-assessment for CT, safe DICOM, segmentation, patient mesh, registration, distillation, FHIR export, year-1 closure | K10: G0-R (CT), G1-D (lần 2), G6 | L10: v2.0 | M10: =COUNTIF('Daily Plan'!$F$4:$F$263,A10) -> 60 | N10: =COUNTIFS('Daily Plan'!$F$4:$F$263,A10,'Daily Plan'!$P$4:$P$263,"Xong") -> 0 | O10: =IFERROR(N10/M10,0) -> 0 | P10: =SUMIFS('Daily Plan'!$N$4:$N$263,'Daily Plan'!$F$4:$F$263,A10) -> 240 | Q10: =SUMIFS('Daily Plan'!$O$4:$O$263,'Daily Plan'!$F$4:$F$263,A10) -> 0
A11: Tổng / Total | M11: =SUM(M4:M10) -> 260 | N11: =SUM(N4:N10) -> 0 | O11: =IFERROR(N11/M11,0) -> 0 | P11: =SUM(P4:P10) -> 1040 | Q11: =SUM(Q4:Q10) -> 0

Sheet Gantt
A1: Gantt 52 tuần / 52-week Gantt
A2: Mỗi ô = 1 tuần kế hoạch (5 ngày làm việc). ◆ = tuần có cổng. Hàng 4: ngày bắt đầu tuần, tính từ Daily Plan.
A3: Sprint | B3: Phase | C3: 1 | D3: 2 | E3: 3 | F3: 4 | G3: 5 | H3: 6 | I3: 7 | J3: 8 | K3: 9 | L3: 10 | M3: 11 | N3: 12 | O3: 13 | P3: 14 | Q3: 15 | R3: 16 | S3: 17 | T3: 18 | U3: 19 | V3: 20 | W3: 21 | X3: 22 | Y3: 23 | Z3: 24 | AA3: 25 | AB3: 26 | AC3: 27 | AD3: 28 | AE3: 29 | AF3: 30 | AG3: 31 | AH3: 32 | AI3: 33 | AJ3: 34 | AK3: 35 | AL3: 36 | AM3: 37 | AN3: 38 | AO3: 39 | AP3: 40 | AQ3: 41 | AR3: 42 | AS3: 43 | AT3: 44 | AU3: 45 | AV3: 46 | AW3: 47 | AX3: 48 | AY3: 49 | AZ3: 50 | BA3: 51 | BB3: 52
A4: Bắt đầu tuần | C4: =INDEX('Daily Plan'!$B$4:$B$263,1) -> 46314 | D4: =INDEX('Daily Plan'!$B$4:$B$263,6) -> 46321 | E4: =INDEX('Daily Plan'!$B$4:$B$263,11) -> 46328 | F4: =INDEX('Daily Plan'!$B$4:$B$263,16) -> 46335 | G4: =INDEX('Daily Plan'!$B$4:$B$263,21) -> 46342 | H4: =INDEX('Daily Plan'!$B$4:$B$263,26) -> 46349 | I4: =INDEX('Daily Plan'!$B$4:$B$263,31) -> 46357 | J4: =INDEX('Daily Plan'!$B$4:$B$263,36) -> 46364 | K4: =INDEX('Daily Plan'!$B$4:$B$263,41) -> 46371 | L4: =INDEX('Daily Plan'!$B$4:$B$263,46) -> 46378 | M4: =INDEX('Daily Plan'!$B$4:$B$263,51) -> 46385 | N4: =INDEX('Daily Plan'!$B$4:$B$263,56) -> 46393 | O4: =INDEX('Daily Plan'!$B$4:$B$263,61) -> 46400 | P4: =INDEX('Daily Plan'!$B$4:$B$263,66) -> 46407 | Q4: =INDEX('Daily Plan'!$B$4:$B$263,71) -> 46414 | R4: =INDEX('Daily Plan'!$B$4:$B$263,76) -> 46421 | S4: =INDEX('Daily Plan'!$B$4:$B$263,81) -> 46435 | T4: =INDEX('Daily Plan'!$B$4:$B$263,86) -> 46442 | U4: =INDEX('Daily Plan'!$B$4:$B$263,91) -> 46449 | V4: =INDEX('Daily Plan'!$B$4:$B$263,96) -> 46456 | W4: =INDEX('Daily Plan'!$B$4:$B$263,101) -> 46463 | X4: =INDEX('Daily Plan'!$B$4:$B$263,106) -> 46470 | Y4: =INDEX('Daily Plan'!$B$4:$B$263,111) -> 46477 | Z4: =INDEX('Daily Plan'!$B$4:$B$263,116) -> 46484 | AA4: =INDEX('Daily Plan'!$B$4:$B$263,121) -> 46491 | AB4: =INDEX('Daily Plan'!$B$4:$B$263,126) -> 46499 | AC4: =INDEX('Daily Plan'!$B$4:$B$263,131) -> 46506 | AD4: =INDEX('Daily Plan'!$B$4:$B$263,136) -> 46514 | AE4: =INDEX('Daily Plan'!$B$4:$B$263,141) -> 46521 | AF4: =INDEX('Daily Plan'!$B$4:$B$263,146) -> 46528 | AG4: =INDEX('Daily Plan'!$B$4:$B$263,151) -> 46535 | AH4: =INDEX('Daily Plan'!$B$4:$B$263,156) -> 46542 | AI4: =INDEX('Daily Plan'!$B$4:$B$263,161) -> 46549 | AJ4: =INDEX('Daily Plan'!$B$4:$B$263,166) -> 46556 | AK4: =INDEX('Daily Plan'!$B$4:$B$263,171) -> 46563 | AL4: =INDEX('Daily Plan'!$B$4:$B$263,176) -> 46570 | AM4: =INDEX('Daily Plan'!$B$4:$B$263,181) -> 46577 | AN4: =INDEX('Daily Plan'!$B$4:$B$263,186) -> 46584 | AO4: =INDEX('Daily Plan'!$B$4:$B$263,191) -> 46591 | AP4: =INDEX('Daily Plan'!$B$4:$B$263,196) -> 46598 | AQ4: =INDEX('Daily Plan'!$B$4:$B$263,201) -> 46605 | AR4: =INDEX('Daily Plan'!$B$4:$B$263,206) -> 46612 | AS4: =INDEX('Daily Plan'!$B$4:$B$263,211) -> 46619 | AT4: =INDEX('Daily Plan'!$B$4:$B$263,216) -> 46626 | AU4: =INDEX('Daily Plan'!$B$4:$B$263,221) -> 46637 | AV4: =INDEX('Daily Plan'!$B$4:$B$263,226) -> 46644 | AW4: =INDEX('Daily Plan'!$B$4:$B$263,231) -> 46651 | AX4: =INDEX('Daily Plan'!$B$4:$B$263,236) -> 46658 | AY4: =INDEX('Daily Plan'!$B$4:$B$263,241) -> 46665 | AZ4: =INDEX('Daily Plan'!$B$4:$B$263,246) -> 46672 | BA4: =INDEX('Daily Plan'!$B$4:$B$263,251) -> 46679 | BB4: =INDEX('Daily Plan'!$B$4:$B$263,256) -> 46686
A5: S01 | B5: P0 · Khởi tạo & Discovery
A6: S02 | B6: P0 · Khởi tạo & Discovery | F6: ◆
A7: S03 | B7: P1 · Foundation
A8: S04 | B8: P1 · Foundation
A9: S05 | B9: P1 · Foundation | L9: ◆
A10: S06 | B10: P2 · Build MVP
A11: S07 | B11: P2 · Build MVP
A12: S08 | B12: P2 · Build MVP
A13: S09 | B13: P2 · Build MVP
A14: S10 | B14: P2 · Build MVP
A15: S11 | B15: P2 · Build MVP | X15: ◆
A16: S12 | B16: P3 · Hardening
A17: S13 | B17: P3 · Hardening | AB17: ◆
A18: S14 | B18: P3 · Hardening | AD18: ◆
A19: S15 | B19: P4 · Beta & Launch v1.0
A20: S16 | B20: P4 · Beta & Launch v1.0 | AH20: ◆
A21: S17 | B21: P5 · Hypercare & v1.5
A22: S18 | B22: P5 · Hypercare & v1.5 | AL22: ◆
A23: S19 | B23: P5 · Hypercare & v1.5
A24: S20 | B24: P5 · Hypercare & v1.5 | AP24: ◆
A25: S21 | B25: P6 · v2.0 — CT & giải phẫu cá nhân | AR25: ◆
A26: S22 | B26: P6 · v2.0 — CT & giải phẫu cá nhân | AT26: ◆
A27: S23 | B27: P6 · v2.0 — CT & giải phẫu cá nhân
A28: S24 | B28: P6 · v2.0 — CT & giải phẫu cá nhân
A29: S25 | B29: P6 · v2.0 — CT & giải phẫu cá nhân
A30: S26 | B30: P6 · v2.0 — CT & giải phẫu cá nhân | BB30: ◆
A32: Chú giải màu phase:
B33: P0 · Khởi tạo & Discovery / Initiation & Discovery
B34: P1 · Foundation / Foundation
B35: P2 · Build MVP / Build MVP
B36: P3 · Hardening / Hardening
B37: P4 · Beta & Launch v1.0 / Beta & Launch v1.0
B38: P5 · Hypercare & v1.5 / Hypercare & v1.5
B39: P6 · v2.0 — CT & giải phẫu cá nhân / v2.0 — CT & patient-specific anatomy

Sheet Sprints
A1: 26 sprint / Sprint overview
A2: Ngày bắt đầu/kết thúc, giờ và % xong tự tính từ Daily Plan.
A3: Sprint | B3: Phase | C3: Tuần KH | D3: Bắt đầu | E3: Kết thúc | F3: Mục tiêu sprint (VI) | G3: Sprint goal (EN) | H3: Demo cuối sprint | I3: Cổng | J3: Role trong sprint (kế hoạch gốc) | K3: Rủi ro trọng tâm | L3: Giờ KH | M3: Giờ TT | N3: Việc xong | O3: % xong
A4: S01 | B4: P0 · Khởi tạo & Discovery | C4: 1–2 | D4: =INDEX('Daily Plan'!$B$4:$B$263,MATCH(A4,'Daily Plan'!$C$4:$C$263,0)) -> 46314 | E4: =INDEX('Daily Plan'!$B$4:$B$263,MATCH(A4,'Daily Plan'!$C$4:$C$263,0)+9) -> 46325 | F4: Khởi tạo dự án: charter, intended use, nghiên cứu người dùng | G4: Initiate the project: charter, intended use, user research | H4: Charter + Intended Use + tổng hợp 5 cuộc phỏng vấn | J4: PM, REG, BA, UX, CSO | K4: Bỏ qua khởi tạo vì muốn code ngay | L4: =SUMIFS('Daily Plan'!$N$4:$N$263,'Daily Plan'!$C$4:$C$263,A4) -> 40 | M4: =SUMIFS('Daily Plan'!$O$4:$O$263,'Daily Plan'!$C$4:$C$263,A4) -> 0 | N4: =COUNTIFS('Daily Plan'!$C$4:$C$263,A4,'Daily Plan'!$P$4:$P$263,"Xong") -> 0 | O4: =IFERROR(N4/COUNTIF('Daily Plan'!$C$4:$C$263,A4),0) -> 0
A5: S02 | B5: P0 · Khởi tạo & Discovery | C5: 3–4 | D5: =INDEX('Daily Plan'!$B$4:$B$263,MATCH(A5,'Daily Plan'!$C$4:$C$263,0)) -> 46328 | E5: =INDEX('Daily Plan'!$B$4:$B$263,MATCH(A5,'Daily Plan'!$C$4:$C$263,0)+9) -> 46339 | F5: Khóa phạm vi MVP, BRD, prototype, golden set v0, chọn OCR → G0, G0-R | G5: Lock MVP scope, BRD, prototype, golden set v0, OCR choice → G0, G0-R | H5: Prototype click-through + báo cáo bake-off OCR | I5: G0, G0-R | J5: BA, UX, AI, DC, SA, REG, QC | K5: Scope creep: muốn làm mọi Khoa cùng lúc | L5: =SUMIFS('Daily Plan'!$N$4:$N$263,'Daily Plan'!$C$4:$C$263,A5) -> 40 | M5: =SUMIFS('Daily Plan'!$O$4:$O$263,'Daily Plan'!$C$4:$C$263,A5) -> 0 | N5: =COUNTIFS('Daily Plan'!$C$4:$C$263,A5,'Daily Plan'!$P$4:$P$263,"Xong") -> 0 | O5: =IFERROR(N5/COUNTIF('Daily Plan'!$C$4:$C$263,A5),0) -> 0
A6: S03 | B6: P1 · Foundation | C6: 5–6 | D6: =INDEX('Daily Plan'!$B$4:$B$263,MATCH(A6,'Daily Plan'!$C$4:$C$263,0)) -> 46342 | E6: =INDEX('Daily Plan'!$B$4:$B$263,MATCH(A6,'Daily Plan'!$C$4:$C$263,0)+9) -> 46356 | F6: Nền móng kỹ thuật: repo, CI, landing zone AWS, VPC Terraform, khung auth | G6: Engineering foundation: repo, CI, AWS landing zone, Terraform VPC, auth skeleton | H6: Đăng nhập → trang trống trên môi trường nonprod | J6: SA, OPS, BE, FE, SEC, PM | K6: Sa đà hạ tầng > 25% thời gian sprint | L6: =SUMIFS('Daily Plan'!$N$4:$N$263,'Daily Plan'!$C$4:$C$263,A6) -> 40 | M6: =SUMIFS('Daily Plan'!$O$4:$O$263,'Daily Plan'!$C$4:$C$263,A6) -> 0 | N6: =COUNTIFS('Daily Plan'!$C$4:$C$263,A6,'Daily Plan'!$P$4:$P$263,"Xong") -> 0 | O6: =IFERROR(N6/COUNTIF('Daily Plan'!$C$4:$C$263,A6),0) -> 0
A7: S04 | B7: P1 · Foundation | C7: 7–8 | D7: =INDEX('Daily Plan'!$B$4:$B$263,MATCH(A7,'Daily Plan'!$C$4:$C$263,0)) -> 46357 | E7: =INDEX('Daily Plan'!$B$4:$B$263,MATCH(A7,'Daily Plan'!$C$4:$C$263,0)+9) -> 46370 | F7: Data model, ranh giới PHI mức A, upload an toàn, design system | G7: Data model, level-A PHI boundary, secure upload, design system | H7: Upload ảnh vào bucket quarantine; file độc bị chặn | J7: BE, OPS, UX, FE, DE, QA | K7: Lộ PHI do thiết kế schema sai | L7: =SUMIFS('Daily Plan'!$N$4:$N$263,'Daily Plan'!$C$4:$C$263,A7) -> 40 | M7: =SUMIFS('Daily Plan'!$O$4:$O$263,'Daily Plan'!$C$4:$C$263,A7) -> 0 | N7: =COUNTIFS('Daily Plan'!$C$4:$C$263,A7,'Daily Plan'!$P$4:$P$263,"Xong") -> 0 | O7: =IFERROR(N7/COUNTIF('Daily Plan'!$C$4:$C$263,A7),0) -> 0
A8: S05 | B8: P1 · Foundation | C8: 9–10 | D8: =INDEX('Daily Plan'!$B$4:$B$263,MATCH(A8,'Daily Plan'!$C$4:$C$263,0)) -> 46371 | E8: =INDEX('Daily Plan'!$B$4:$B$263,MATCH(A8,'Daily Plan'!$C$4:$C$263,0)+9) -> 46384 | F8: Pipeline AI tối giản end-to-end trên staging; AI Gateway v0 → G1, G1-D (dữ liệu đánh giá) | G8: Minimal end-to-end AI pipeline on staging; AI Gateway v0 → G1, G1-D (evaluation data) | H8: 1 ảnh bệnh án → JSON có trích dẫn trên staging | I8: G1-D, G1 | J8: AI, MLO, OPS, CIN, DC, QC | K8: LLM bịa thông tin; chi phí token tăng | L8: =SUMIFS('Daily Plan'!$N$4:$N$263,'Daily Plan'!$C$4:$C$263,A8) -> 40 | M8: =SUMIFS('Daily Plan'!$O$4:$O$263,'Daily Plan'!$C$4:$C$263,A8) -> 0 | N8: =COUNTIFS('Daily Plan'!$C$4:$C$263,A8,'Daily Plan'!$P$4:$P$263,"Xong") -> 0 | O8: =IFERROR(N8/COUNTIF('Daily Plan'!$C$4:$C$263,A8),0) -> 0
A9: S06 | B9: P2 · Build MVP | C9: 11–12 | D9: =INDEX('Daily Plan'!$B$4:$B$263,MATCH(A9,'Daily Plan'!$C$4:$C$263,0)) -> 46385 | E9: =INDEX('Daily Plan'!$B$4:$B$263,MATCH(A9,'Daily Plan'!$C$4:$C$263,0)+9) -> 46399 | F9: Upload an toàn + state machine + OCR, trạng thái realtime | G9: Secure upload + state machine + OCR with realtime status | H9: Upload ảnh, thấy text OCR và trạng thái realtime | J9: BA, FE, BE, AI, QA, SEC, TW, PM | K9: OCR kém với ảnh điện thoại | L9: =SUMIFS('Daily Plan'!$N$4:$N$263,'Daily Plan'!$C$4:$C$263,A9) -> 40 | M9: =SUMIFS('Daily Plan'!$O$4:$O$263,'Daily Plan'!$C$4:$C$263,A9) -> 0 | N9: =COUNTIFS('Daily Plan'!$C$4:$C$263,A9,'Daily Plan'!$P$4:$P$263,"Xong") -> 0 | O9: =IFERROR(N9/COUNTIF('Daily Plan'!$C$4:$C$263,A9),0) -> 0
A10: S07 | B10: P2 · Build MVP | C10: 13–14 | D10: =INDEX('Daily Plan'!$B$4:$B$263,MATCH(A10,'Daily Plan'!$C$4:$C$263,0)) -> 46400 | E10: =INDEX('Daily Plan'!$B$4:$B$263,MATCH(A10,'Daily Plan'!$C$4:$C$263,0)+9) -> 46413 | F10: Trích xuất LLM + màn Review + cascade model v1 | G10: LLM extraction + Review screen + model cascade v1 | H10: Sửa và xác nhận kết quả, highlight bounding box | J10: AI, BE, FE, MLO, QA, CSO, DE, PM | K10: Hallucination; người dùng tin AI tuyệt đối | L10: =SUMIFS('Daily Plan'!$N$4:$N$263,'Daily Plan'!$C$4:$C$263,A10) -> 40 | M10: =SUMIFS('Daily Plan'!$O$4:$O$263,'Daily Plan'!$C$4:$C$263,A10) -> 0 | N10: =COUNTIFS('Daily Plan'!$C$4:$C$263,A10,'Daily Plan'!$P$4:$P$263,"Xong") -> 0 | O10: =IFERROR(N10/COUNTIF('Daily Plan'!$C$4:$C$263,A10),0) -> 0
A11: S08 | B11: P2 · Build MVP | C11: 15–16 | D11: =INDEX('Daily Plan'!$B$4:$B$263,MATCH(A11,'Daily Plan'!$C$4:$C$263,0)) -> 46414 | E11: =INDEX('Daily Plan'!$B$4:$B$263,MATCH(A11,'Daily Plan'!$C$4:$C$263,0)+9) -> 46434 | F11: Viewer 2D toàn thân + Unit Răng hàm mặt | G11: 2D whole-body viewer + Dental Unit | H11: Sơ đồ răng FDI tô màu theo bệnh án | J11: UX, ART, FE, BE, AI, CIN, QA, CSO, PM | K11: Sai số răng/bên | L11: =SUMIFS('Daily Plan'!$N$4:$N$263,'Daily Plan'!$C$4:$C$263,A11) -> 40 | M11: =SUMIFS('Daily Plan'!$O$4:$O$263,'Daily Plan'!$C$4:$C$263,A11) -> 0 | N11: =COUNTIFS('Daily Plan'!$C$4:$C$263,A11,'Daily Plan'!$P$4:$P$263,"Xong") -> 0 | O11: =IFERROR(N11/COUNTIF('Daily Plan'!$C$4:$C$263,A11),0) -> 0
A12: S09 | B12: P2 · Build MVP | C12: 17–18 | D12: =INDEX('Daily Plan'!$B$4:$B$263,MATCH(A12,'Daily Plan'!$C$4:$C$263,0)) -> 46435 | E12: =INDEX('Daily Plan'!$B$4:$B$263,MATCH(A12,'Daily Plan'!$C$4:$C$263,0)+9) -> 46448 | F12: Viewer 3D + Unit Tim mạch | G12: 3D viewer + Cardiology Unit | H12: Xoay/zoom mô hình, bấm vùng xem chi tiết | J12: FE, ART, BE, AI, UX, QA, SEC, PM | K12: 3D giật trên máy yếu | L12: =SUMIFS('Daily Plan'!$N$4:$N$263,'Daily Plan'!$C$4:$C$263,A12) -> 40 | M12: =SUMIFS('Daily Plan'!$O$4:$O$263,'Daily Plan'!$C$4:$C$263,A12) -> 0 | N12: =COUNTIFS('Daily Plan'!$C$4:$C$263,A12,'Daily Plan'!$P$4:$P$263,"Xong") -> 0 | O12: =IFERROR(N12/COUNTIF('Daily Plan'!$C$4:$C$263,A12),0) -> 0
A13: S10 | B13: P2 · Build MVP | C13: 19–20 | D13: =INDEX('Daily Plan'!$B$4:$B$263,MATCH(A13,'Daily Plan'!$C$4:$C$263,0)) -> 46449 | E13: =INDEX('Daily Plan'!$B$4:$B$263,MATCH(A13,'Daily Plan'!$C$4:$C$263,0)+9) -> 46462 | F13: Unit Ung bướu + giải thích RAG có guardrail | G13: Oncology Unit + guarded RAG explanations | H13: Khối u, hạch, di căn; hỏi đáp có trích dẫn | J13: BA, AI, FE, TW, MLO, QA, CSO, PM | K13: Hình ảnh ung thư gây sợ; trả lời vượt phạm vi | L13: =SUMIFS('Daily Plan'!$N$4:$N$263,'Daily Plan'!$C$4:$C$263,A13) -> 40 | M13: =SUMIFS('Daily Plan'!$O$4:$O$263,'Daily Plan'!$C$4:$C$263,A13) -> 0 | N13: =COUNTIFS('Daily Plan'!$C$4:$C$263,A13,'Daily Plan'!$P$4:$P$263,"Xong") -> 0 | O13: =IFERROR(N13/COUNTIF('Daily Plan'!$C$4:$C$263,A13),0) -> 0
A14: S11 | B14: P2 · Build MVP | C14: 21–22 | D14: =INDEX('Daily Plan'!$B$4:$B$263,MATCH(A14,'Daily Plan'!$C$4:$C$263,0)) -> 46463 | E14: =INDEX('Daily Plan'!$B$4:$B$263,MATCH(A14,'Daily Plan'!$C$4:$C$263,0)+9) -> 46476 | F14: Timeline pre/post, mô tả bằng text, chia sẻ, admin, quyền dữ liệu → G2 | G14: Pre/post timeline, text descriptions, sharing, admin, data rights → G2 | H14: So sánh hai lần khám, chia sẻ có hạn cho bác sĩ | I14: G2 | J14: FE, BE, QA, AI, TW, QC | K14: Lỗi phân quyền khi chia sẻ | L14: =SUMIFS('Daily Plan'!$N$4:$N$263,'Daily Plan'!$C$4:$C$263,A14) -> 40 | M14: =SUMIFS('Daily Plan'!$O$4:$O$263,'Daily Plan'!$C$4:$C$263,A14) -> 0 | N14: =COUNTIFS('Daily Plan'!$C$4:$C$263,A14,'Daily Plan'!$P$4:$P$263,"Xong") -> 0 | O14: =IFERROR(N14/COUNTIF('Daily Plan'!$C$4:$C$263,A14),0) -> 0
A15: S12 | B15: P3 · Hardening | C15: 23–24 | D15: =INDEX('Daily Plan'!$B$4:$B$263,MATCH(A15,'Daily Plan'!$C$4:$C$263,0)) -> 46477 | E15: =INDEX('Daily Plan'!$B$4:$B$263,MATCH(A15,'Daily Plan'!$C$4:$C$263,0)+9) -> 46490 | F15: Bảo mật mức B, hiệu năng, khả năng truy cập | G15: Level-B security, performance, accessibility | H15: Báo cáo load test + DAST sạch + kiến trúc mức B | J15: SEC, OPS, BE, QA, FE, SRE, PM | K15: Phát hiện lỗ hổng muộn | L15: =SUMIFS('Daily Plan'!$N$4:$N$263,'Daily Plan'!$C$4:$C$263,A15) -> 40 | M15: =SUMIFS('Daily Plan'!$O$4:$O$263,'Daily Plan'!$C$4:$C$263,A15) -> 0 | N15: =COUNTIFS('Daily Plan'!$C$4:$C$263,A15,'Daily Plan'!$P$4:$P$263,"Xong") -> 0 | O15: =IFERROR(N15/COUNTIF('Daily Plan'!$C$4:$C$263,A15),0) -> 0
A16: S13 | B16: P3 · Hardening | C16: 25–26 | D16: =INDEX('Daily Plan'!$B$4:$B$263,MATCH(A16,'Daily Plan'!$C$4:$C$263,0)) -> 46491 | E16: =INDEX('Daily Plan'!$B$4:$B$263,MATCH(A16,'Daily Plan'!$C$4:$C$263,0)+9) -> 46505 | F16: An toàn lâm sàng, pháp lý, usability tổng kết → G2-CS | G16: Clinical safety, regulatory, summative usability → G2-CS | H16: Clinical Safety Case + kết quả xác thực bởi bác sĩ | I16: G2-CS | J16: CSO, UX, REG, SEC, SRE, QC | K16: Không có bác sĩ thật ký duyệt | L16: =SUMIFS('Daily Plan'!$N$4:$N$263,'Daily Plan'!$C$4:$C$263,A16) -> 40 | M16: =SUMIFS('Daily Plan'!$O$4:$O$263,'Daily Plan'!$C$4:$C$263,A16) -> 0 | N16: =COUNTIFS('Daily Plan'!$C$4:$C$263,A16,'Daily Plan'!$P$4:$P$263,"Xong") -> 0 | O16: =IFERROR(N16/COUNTIF('Daily Plan'!$C$4:$C$263,A16),0) -> 0
A17: S14 | B17: P3 · Hardening | C17: 27–28 | D17: =INDEX('Daily Plan'!$B$4:$B$263,MATCH(A17,'Daily Plan'!$C$4:$C$263,0)) -> 46506 | E17: =INDEX('Daily Plan'!$B$4:$B$263,MATCH(A17,'Daily Plan'!$C$4:$C$263,0)+9) -> 46520 | F17: Pentest độc lập, UAT, prod sẵn sàng → G3, G3-P | G17: Independent pentest, UAT, production ready → G3, G3-P | H17: Readiness report GO + prod rollback test | I17: G3, G3-P | J17: SEC, BE, AI, QA, TW, SUP, OPS, QC | K17: Finding High phải sửa gấp làm trễ launch | L17: =SUMIFS('Daily Plan'!$N$4:$N$263,'Daily Plan'!$C$4:$C$263,A17) -> 40 | M17: =SUMIFS('Daily Plan'!$O$4:$O$263,'Daily Plan'!$C$4:$C$263,A17) -> 0 | N17: =COUNTIFS('Daily Plan'!$C$4:$C$263,A17,'Daily Plan'!$P$4:$P$263,"Xong") -> 0 | O17: =IFERROR(N17/COUNTIF('Daily Plan'!$C$4:$C$263,A17),0) -> 0
A18: S15 | B18: P4 · Beta & Launch v1.0 | C18: 29–30 | D18: =INDEX('Daily Plan'!$B$4:$B$263,MATCH(A18,'Daily Plan'!$C$4:$C$263,0)) -> 46521 | E18: =INDEX('Daily Plan'!$B$4:$B$263,MATCH(A18,'Daily Plan'!$C$4:$C$263,0)+9) -> 46534 | F18: Beta kín 10–20 người | G18: Closed beta with 10–20 users | H18: Báo cáo beta tuần 1–2 | J18: PM, OPS, SUP, SRE, BA, BE, AI, CSO, DE | K18: Người beta dùng dữ liệu thật trước khi sẵn sàng | L18: =SUMIFS('Daily Plan'!$N$4:$N$263,'Daily Plan'!$C$4:$C$263,A18) -> 40 | M18: =SUMIFS('Daily Plan'!$O$4:$O$263,'Daily Plan'!$C$4:$C$263,A18) -> 0 | N18: =COUNTIFS('Daily Plan'!$C$4:$C$263,A18,'Daily Plan'!$P$4:$P$263,"Xong") -> 0 | O18: =IFERROR(N18/COUNTIF('Daily Plan'!$C$4:$C$263,A18),0) -> 0
A19: S16 | B19: P4 · Beta & Launch v1.0 | C19: 31–32 | D19: =INDEX('Daily Plan'!$B$4:$B$263,MATCH(A19,'Daily Plan'!$C$4:$C$263,0)) -> 46535 | E19: =INDEX('Daily Plan'!$B$4:$B$263,MATCH(A19,'Daily Plan'!$C$4:$C$263,0)+9) -> 46548 | F19: Phát hành v1.0 → G4 | G19: Release v1.0 → G4 | H19: v1.0 chạy trên prod + báo cáo tuần đầu | I19: G4 | J19: PM, QA, TW, QC, OPS, SRE, SUP, FE, DE | K19: Sự cố ngày đầu ra mắt | L19: =SUMIFS('Daily Plan'!$N$4:$N$263,'Daily Plan'!$C$4:$C$263,A19) -> 40 | M19: =SUMIFS('Daily Plan'!$O$4:$O$263,'Daily Plan'!$C$4:$C$263,A19) -> 0 | N19: =COUNTIFS('Daily Plan'!$C$4:$C$263,A19,'Daily Plan'!$P$4:$P$263,"Xong") -> 0 | O19: =IFERROR(N19/COUNTIF('Daily Plan'!$C$4:$C$263,A19),0) -> 0
A20: S17 | B20: P5 · Hypercare & v1.5 | C20: 33–34 | D20: =INDEX('Daily Plan'!$B$4:$B$263,MATCH(A20,'Daily Plan'!$C$4:$C$263,0)) -> 46549 | E20: =INDEX('Daily Plan'!$B$4:$B$263,MATCH(A20,'Daily Plan'!$C$4:$C$263,0)+9) -> 46562 | F20: Hypercare + nhập bệnh án số (PDF có lớp chữ, DOCX, FHIR) | G20: Hypercare + digital record import (text-layer PDF, DOCX, FHIR) | H20: Nhập PDF/FHIR → finding không qua OCR/LLM | J20: PM, BE, CIN, QA, AI, MLO, SUP, SRE | K20: File nhập độc hại; FHIR không chuẩn | L20: =SUMIFS('Daily Plan'!$N$4:$N$263,'Daily Plan'!$C$4:$C$263,A20) -> 40 | M20: =SUMIFS('Daily Plan'!$O$4:$O$263,'Daily Plan'!$C$4:$C$263,A20) -> 0 | N20: =COUNTIFS('Daily Plan'!$C$4:$C$263,A20,'Daily Plan'!$P$4:$P$263,"Xong") -> 0 | O20: =IFERROR(N20/COUNTIF('Daily Plan'!$C$4:$C$263,A20),0) -> 0
A21: S18 | B21: P5 · Hypercare & v1.5 | C21: 35–36 | D21: =INDEX('Daily Plan'!$B$4:$B$263,MATCH(A21,'Daily Plan'!$C$4:$C$263,0)) -> 46563 | E21: =INDEX('Daily Plan'!$B$4:$B$263,MATCH(A21,'Daily Plan'!$C$4:$C$263,0)+9) -> 46576 | F21: Thư viện template giải phẫu + data donation opt-in → G5-H | G21: Anatomy template library + opt-in data donation → G5-H | H21: Template theo giới/tuổi, ẩn cơ quan đã cắt, biểu tượng implant | I21: G5-H | J21: UX, ART, FE, BE, REG, DC, QA, CSO, SUP, QC | K21: Hiển thị sai giải phẫu đặc biệt | L21: =SUMIFS('Daily Plan'!$N$4:$N$263,'Daily Plan'!$C$4:$C$263,A21) -> 40 | M21: =SUMIFS('Daily Plan'!$O$4:$O$263,'Daily Plan'!$C$4:$C$263,A21) -> 0 | N21: =COUNTIFS('Daily Plan'!$C$4:$C$263,A21,'Daily Plan'!$P$4:$P$263,"Xong") -> 0 | O21: =IFERROR(N21/COUNTIF('Daily Plan'!$C$4:$C$263,A21),0) -> 0
A22: S19 | B22: P5 · Hypercare & v1.5 | C22: 37–38 | D22: =INDEX('Daily Plan'!$B$4:$B$263,MATCH(A22,'Daily Plan'!$C$4:$C$263,0)) -> 46577 | E22: =INDEX('Daily Plan'!$B$4:$B$263,MATCH(A22,'Daily Plan'!$C$4:$C$263,0)+9) -> 46590 | F22: Thêm Unit Hô hấp, Thận–Tiết niệu + cascade model đầy đủ | G22: Add Respiratory and Nephrology–Urology Units + full model cascade | H22: 2 Unit mới + dashboard chi phí theo tầng | J22: BA, ART, BE, AI, MLO, FE, CIN, QA, PM | K22: Chi phí tăng khi thêm Unit | L22: =SUMIFS('Daily Plan'!$N$4:$N$263,'Daily Plan'!$C$4:$C$263,A22) -> 40 | M22: =SUMIFS('Daily Plan'!$O$4:$O$263,'Daily Plan'!$C$4:$C$263,A22) -> 0 | N22: =COUNTIFS('Daily Plan'!$C$4:$C$263,A22,'Daily Plan'!$P$4:$P$263,"Xong") -> 0 | O22: =IFERROR(N22/COUNTIF('Daily Plan'!$C$4:$C$263,A22),0) -> 0
A23: S20 | B23: P5 · Hypercare & v1.5 | C23: 39–40 | D23: =INDEX('Daily Plan'!$B$4:$B$263,MATCH(A23,'Daily Plan'!$C$4:$C$263,0)) -> 46591 | E23: =INDEX('Daily Plan'!$B$4:$B$263,MATCH(A23,'Daily Plan'!$C$4:$C$263,0)+9) -> 46604 | F23: Hợp tác dữ liệu, gán nhãn, phát hành v1.5 → G5 | G23: Data partnership, annotation, v1.5 release → G5 | H23: Kết quả gán nhãn thử (kappa) + v1.5 trên prod | I23: G5 | J23: PM, REG, DC, AI, SEC, QA, TW, OPS, QC | K23: Nhãn kém chất lượng; vướng thỏa thuận dữ liệu | L23: =SUMIFS('Daily Plan'!$N$4:$N$263,'Daily Plan'!$C$4:$C$263,A23) -> 40 | M23: =SUMIFS('Daily Plan'!$O$4:$O$263,'Daily Plan'!$C$4:$C$263,A23) -> 0 | N23: =COUNTIFS('Daily Plan'!$C$4:$C$263,A23,'Daily Plan'!$P$4:$P$263,"Xong") -> 0 | O23: =IFERROR(N23/COUNTIF('Daily Plan'!$C$4:$C$263,A23),0) -> 0
A24: S21 | B24: P6 · v2.0 — CT & giải phẫu cá nhân | C24: 41–42 | D24: =INDEX('Daily Plan'!$B$4:$B$263,MATCH(A24,'Daily Plan'!$C$4:$C$263,0)) -> 46605 | E24: =INDEX('Daily Plan'!$B$4:$B$263,MATCH(A24,'Daily Plan'!$C$4:$C$263,0)+9) -> 46618 | F24: Tái đánh giá pháp lý cho CT + tiếp nhận DICOM an toàn | G24: Regulatory re-assessment for CT + safe DICOM intake | H24: Upload series CT → DICOM đã khử định danh | I24: G0-R (CT) | J24: REG, IMG, SA, SEC, BE, DC, CSO, QA, QC | K24: Vượt ranh giới SaMD; PHI trong header/ảnh | L24: =SUMIFS('Daily Plan'!$N$4:$N$263,'Daily Plan'!$C$4:$C$263,A24) -> 40 | M24: =SUMIFS('Daily Plan'!$O$4:$O$263,'Daily Plan'!$C$4:$C$263,A24) -> 0 | N24: =COUNTIFS('Daily Plan'!$C$4:$C$263,A24,'Daily Plan'!$P$4:$P$263,"Xong") -> 0 | O24: =IFERROR(N24/COUNTIF('Daily Plan'!$C$4:$C$263,A24),0) -> 0
A25: S22 | B25: P6 · v2.0 — CT & giải phẫu cá nhân | C25: 43–44 | D25: =INDEX('Daily Plan'!$B$4:$B$263,MATCH(A25,'Daily Plan'!$C$4:$C$263,0)) -> 46619 | E25: =INDEX('Daily Plan'!$B$4:$B$263,MATCH(A25,'Daily Plan'!$C$4:$C$263,0)+9) -> 46636 | F25: Viewer lát cắt + segmentation + dựng mesh từ CT | G25: Slice viewer + segmentation + mesh from CT | H25: Xem lát cắt và mesh cơ quan dựng từ CT mẫu | I25: G1-D (lần 2) | J25: FE, IMG, MLO, QA, DC, AI, PM | K25: Chi phí GPU; mesh nặng | L25: =SUMIFS('Daily Plan'!$N$4:$N$263,'Daily Plan'!$C$4:$C$263,A25) -> 40 | M25: =SUMIFS('Daily Plan'!$O$4:$O$263,'Daily Plan'!$C$4:$C$263,A25) -> 0 | N25: =COUNTIFS('Daily Plan'!$C$4:$C$263,A25,'Daily Plan'!$P$4:$P$263,"Xong") -> 0 | O25: =IFERROR(N25/COUNTIF('Daily Plan'!$C$4:$C$263,A25),0) -> 0
A26: S23 | B26: P6 · v2.0 — CT & giải phẫu cá nhân | C26: 45–46 | D26: =INDEX('Daily Plan'!$B$4:$B$263,MATCH(A26,'Daily Plan'!$C$4:$C$263,0)) -> 46637 | E26: =INDEX('Daily Plan'!$B$4:$B$263,MATCH(A26,'Daily Plan'!$C$4:$C$263,0)+9) -> 46650 | F26: Căn chỉnh với template (registration) + liên kết báo cáo CT | G26: Template registration + linking CT reports | H26: So sánh template và giải phẫu cá nhân; finding đúng vị trí | J26: IMG, FE, BE, AI, CSO, UX, QA, PM | K26: Sai số căn chỉnh làm lệch vị trí | L26: =SUMIFS('Daily Plan'!$N$4:$N$263,'Daily Plan'!$C$4:$C$263,A26) -> 40 | M26: =SUMIFS('Daily Plan'!$O$4:$O$263,'Daily Plan'!$C$4:$C$263,A26) -> 0 | N26: =COUNTIFS('Daily Plan'!$C$4:$C$263,A26,'Daily Plan'!$P$4:$P$263,"Xong") -> 0 | O26: =IFERROR(N26/COUNTIF('Daily Plan'!$C$4:$C$263,A26),0) -> 0
A27: S24 | B27: P6 · v2.0 — CT & giải phẫu cá nhân | C27: 47–48 | D27: =INDEX('Daily Plan'!$B$4:$B$263,MATCH(A27,'Daily Plan'!$C$4:$C$263,0)) -> 46651 | E27: =INDEX('Daily Plan'!$B$4:$B$263,MATCH(A27,'Daily Plan'!$C$4:$C$263,0)+9) -> 46664 | F27: Distillation + tối ưu chi phí model | G27: Distillation + model cost optimisation | H27: Model nhỏ chạy shadow mode, so sánh chi phí/chất lượng | J27: MLO, AI, DE, SEC, REG, QA, PM | K27: Model nhỏ kém hơn ở ca khó | L27: =SUMIFS('Daily Plan'!$N$4:$N$263,'Daily Plan'!$C$4:$C$263,A27) -> 40 | M27: =SUMIFS('Daily Plan'!$O$4:$O$263,'Daily Plan'!$C$4:$C$263,A27) -> 0 | N27: =COUNTIFS('Daily Plan'!$C$4:$C$263,A27,'Daily Plan'!$P$4:$P$263,"Xong") -> 0 | O27: =IFERROR(N27/COUNTIF('Daily Plan'!$C$4:$C$263,A27),0) -> 0
A28: S25 | B28: P6 · v2.0 — CT & giải phẫu cá nhân | C28: 49–50 | D28: =INDEX('Daily Plan'!$B$4:$B$263,MATCH(A28,'Daily Plan'!$C$4:$C$263,0)) -> 46665 | E28: =INDEX('Daily Plan'!$B$4:$B$263,MATCH(A28,'Daily Plan'!$C$4:$C$263,0)+9) -> 46678 | F28: FHIR export, hardening v2, xác thực lâm sàng CT | G28: FHIR export, v2 hardening, CT clinical validation | H28: Xuất FHIR Bundle hợp lệ; báo cáo xác thực CT | J28: CIN, BE, SEC, CSO, QA, SRE, TW, SUP, QC, PM | K28: Thiếu thời gian hardening trước v2 | L28: =SUMIFS('Daily Plan'!$N$4:$N$263,'Daily Plan'!$C$4:$C$263,A28) -> 40 | M28: =SUMIFS('Daily Plan'!$O$4:$O$263,'Daily Plan'!$C$4:$C$263,A28) -> 0 | N28: =COUNTIFS('Daily Plan'!$C$4:$C$263,A28,'Daily Plan'!$P$4:$P$263,"Xong") -> 0 | O28: =IFERROR(N28/COUNTIF('Daily Plan'!$C$4:$C$263,A28),0) -> 0
A29: S26 | B29: P6 · v2.0 — CT & giải phẫu cá nhân | C29: 51–52 | D29: =INDEX('Daily Plan'!$B$4:$B$263,MATCH(A29,'Daily Plan'!$C$4:$C$263,0)) -> 46679 | E29: =INDEX('Daily Plan'!$B$4:$B$263,MATCH(A29,'Daily Plan'!$C$4:$C$263,0)+9) -> 46692 | F29: Phát hành v2.0 + đóng năm 1 → G6 | G29: Release v2.0 + year-1 closure → G6 | H29: v2.0 trên prod + closure report | I29: G6 | J29: PM, OPS, SRE, REG, TW, QC | K29: Không đóng dự án, thiếu bài học | L29: =SUMIFS('Daily Plan'!$N$4:$N$263,'Daily Plan'!$C$4:$C$263,A29) -> 40 | M29: =SUMIFS('Daily Plan'!$O$4:$O$263,'Daily Plan'!$C$4:$C$263,A29) -> 0 | N29: =COUNTIFS('Daily Plan'!$C$4:$C$263,A29,'Daily Plan'!$P$4:$P$263,"Xong") -> 0 | O29: =IFERROR(N29/COUNTIF('Daily Plan'!$C$4:$C$263,A29),0) -> 0

Sheet Daily Plan
A1: Kế hoạch theo ngày / Daily plan — 260 ngày làm việc
A2: Ô vàng = nhập (Giờ TT, Trạng thái, Ghi chú). Ngày tự tính từ Settings!C4 + Holidays. Cột Skill = skill agent cần gọi.
A3: Ngày # | B3: Ngày / Date | C3: Sprint | D3: Tuần KH | E3: Ngày trong sprint | F3: Phase | G3: Role | H3: Skill (agent) | I3: Việc (VI) | J3: Task (EN) | K3: Đầu ra / Deliverable | L3: Tiêu chí xong (DoD) | M3: Cổng / Gate | N3: Giờ KH | O3: Giờ TT | P3: Trạng thái | Q3: Cảnh báo | R3: Ghi chú
A4: 1 | B4: =WORKDAY(Settings!$C$4-1,A4,Holidays!$A$5:$A$40) -> 46314 | C4: S01 | D4: =INT((A4-1)/5)+1 -> 1 | E4: =MOD(A4-1,10)+1 -> 1 | F4: P0 · Khởi tạo & Discovery | G4: PM | H4: =IFERROR(INDEX(Roles!$D$5:$D$26,MATCH(G4,Roles!$A$5:$A$26,0)),"") -> medilens-product-manager | I4: Sprint Planning (1h); viết Project Charter 2 trang: mục tiêu, phạm vi, ngân sách, tiêu chí thành công | J4: Sprint Planning (1h); write a 2-page Project Charter: goals, scope, budget, success criteria | K4: docs/00-charter.md | L4: ≥ 3 mục tiêu đo được, ngân sách tháng, top-5 rủi ro | N4: =Settings!$C$5 -> 4 | P4: Chưa làm | Q4: =IF(OR(P4="Xong",P4="Bỏ"),"",IF(B4<TODAY(),"Quá hạn",IF(B4=TODAY(),"Hôm nay","")))
A5: 2 | B5: =WORKDAY(Settings!$C$4-1,A5,Holidays!$A$5:$A$40) -> 46315 | C5: S01 | D5: =INT((A5-1)/5)+1 -> 1 | E5: =MOD(A5-1,10)+1 -> 2 | F5: P0 · Khởi tạo & Discovery | G5: PM | H5: =IFERROR(INDEX(Roles!$D$5:$D$26,MATCH(G5,Roles!$A$5:$A$26,0)),"") -> medilens-product-manager | I5: Business case (có phương án 'không làm'); stakeholder register; quản trị: steering = bạn + mentor + bác sĩ cố vấn | J5: Business case incl. do-nothing option; stakeholder register; governance: steering = you + mentor + clinical advisor | K5: business-case.md, stakeholders.md | L5: Steering có tên người, lịch họp cuối mỗi phase, mẫu báo cáo tháng | N5: =Settings!$C$5 -> 4 | P5: Chưa làm | Q5: =IF(OR(P5="Xong",P5="Bỏ"),"",IF(B5<TODAY(),"Quá hạn",IF(B5=TODAY(),"Hôm nay","")))
A6: 3 | B6: =WORKDAY(Settings!$C$4-1,A6,Holidays!$A$5:$A$40) -> 46316 | C6: S01 | D6: =INT((A6-1)/5)+1 -> 1 | E6: =MOD(A6-1,10)+1 -> 3 | F6: P0 · Khởi tạo & Discovery | G6: REG | H6: =IFERROR(INDEX(Roles!$D$5:$D$26,MATCH(G6,Roles!$A$5:$A$26,0)),"") -> medilens-regulatory-privacy-officer | I6: Viết Intended Use Statement và danh sách ngoài phạm vi (không chẩn đoán, không gợi ý điều trị, không phát hiện bệnh trên ảnh) | J6: Write the Intended Use Statement and out-of-scope list (no diagnosis, no treatment advice, no image-based detection) | K6: regulatory/intended-use.md | L6: Không có động từ chẩn đoán; có danh sách từ cấm dùng trong claims | N6: =Settings!$C$5 -> 4 | P6: Chưa làm | Q6: =IF(OR(P6="Xong",P6="Bỏ"),"",IF(B6<TODAY(),"Quá hạn",IF(B6=TODAY(),"Hôm nay","")))
A7: 4 | B7: =WORKDAY(Settings!$C$4-1,A7,Holidays!$A$5:$A$40) -> 46317 | C7: S01 | D7: =INT((A7-1)/5)+1 -> 1 | E7: =MOD(A7-1,10)+1 -> 4 | F7: P0 · Khởi tạo & Discovery | G7: REG | H7: =IFERROR(INDEX(Roles!$D$5:$D$26,MATCH(G7,Roles!$A$5:$A$26,0)),"") -> medilens-regulatory-privacy-officer | I7: Regulatory Decision Record nháp: NĐ 98/2021 (sửa đổi 07/2023, 04/2025), TT 05/2022, Luật BVDLCN 91/2025/QH15, TT 13/2025/TT-BYT | J7: Draft Regulatory Decision Record: Decree 98/2021 (amended 07/2023, 04/2025), Circular 05/2022, PDPL 91/2025/QH15, Circular 13/2025/TT-BYT | K7: regulatory/RDR-001.md | L7: Mỗi kết luận có trích dẫn nguồn và ngày rà soát lại | N7: =Settings!$C$5 -> 4 | P7: Chưa làm | Q7: =IF(OR(P7="Xong",P7="Bỏ"),"",IF(B7<TODAY(),"Quá hạn",IF(B7=TODAY(),"Hôm nay","")))
A8: 5 | B8: =WORKDAY(Settings!$C$4-1,A8,Holidays!$A$5:$A$40) -> 46318 | C8: S01 | D8: =INT((A8-1)/5)+1 -> 1 | E8: =MOD(A8-1,10)+1 -> 5 | F8: P0 · Khởi tạo & Discovery | G8: BA | H8: =IFERROR(INDEX(Roles!$D$5:$D$26,MATCH(G8,Roles!$A$5:$A$26,0)),"") -> medilens-business-analyst | I8: Kế hoạch nghiên cứu người dùng: kịch bản phỏng vấn, mẫu đồng ý tham gia; tuyển 5–8 người (bệnh nhân, người nhà) | J8: User research plan: interview guide, consent form; recruit 5–8 patients/caregivers | K8: research/interview-guide.md | L8: Có mẫu consent; ≥ 5 buổi đã hẹn | N8: =Settings!$C$5 -> 4 | P8: Chưa làm | Q8: =IF(OR(P8="Xong",P8="Bỏ"),"",IF(B8<TODAY(),"Quá hạn",IF(B8=TODAY(),"Hôm nay","")))
A9: 6 | B9: =WORKDAY(Settings!$C$4-1,A9,Holidays!$A$5:$A$40) -> 46321 | C9: S01 | D9: =INT((A9-1)/5)+1 -> 2 | E9: =MOD(A9-1,10)+1 -> 6 | F9: P0 · Khởi tạo & Discovery | G9: BA | H9: =IFERROR(INDEX(Roles!$D$5:$D$26,MATCH(G9,Roles!$A$5:$A$26,0)),"") -> medilens-business-analyst | I9: Phỏng vấn 3 người; viết ghi chú ẩn danh ngay sau mỗi buổi | J9: Run 3 interviews; write anonymised notes right after each | K9: research/notes/ | L9: Ghi chú không chứa tên, SĐT, mã hồ sơ | N9: =Settings!$C$5 -> 4 | P9: Chưa làm | Q9: =IF(OR(P9="Xong",P9="Bỏ"),"",IF(B9<TODAY(),"Quá hạn",IF(B9=TODAY(),"Hôm nay","")))
A10: 7 | B10: =WORKDAY(Settings!$C$4-1,A10,Holidays!$A$5:$A$40) -> 46322 | C10: S01 | D10: =INT((A10-1)/5)+1 -> 2 | E10: =MOD(A10-1,10)+1 -> 7 | F10: P0 · Khởi tạo & Discovery | G10: UX | H10: =IFERROR(INDEX(Roles!$D$5:$D$26,MATCH(G10,Roles!$A$5:$A$26,0)),"") -> medilens-ux-ui-designer | I10: Phỏng vấn 2–3 người còn lại; affinity map các vấn đề | J10: Run the remaining 2–3 interviews; build an affinity map | K10: FigJam affinity map | L10: ≥ 5 cuộc phỏng vấn được gom thành chủ đề | N10: =Settings!$C$5 -> 4 | P10: Chưa làm | Q10: =IF(OR(P10="Xong",P10="Bỏ"),"",IF(B10<TODAY(),"Quá hạn",IF(B10=TODAY(),"Hôm nay","")))
A11: 8 | B11: =WORKDAY(Settings!$C$4-1,A11,Holidays!$A$5:$A$40) -> 46323 | C11: S01 | D11: =INT((A11-1)/5)+1 -> 2 | E11: =MOD(A11-1,10)+1 -> 8 | F11: P0 · Khởi tạo & Discovery | G11: UX | H11: =IFERROR(INDEX(Roles!$D$5:$D$26,MATCH(G11,Roles!$A$5:$A$26,0)),"") -> medilens-ux-ui-designer | I11: Persona (bệnh nhân, người chăm sóc, bác sĩ nhận chia sẻ) + user journey As-Is | J11: Personas (patient, caregiver, receiving clinician) + As-Is user journey | K11: personas, journey-asis | L11: Mỗi pain point dẫn chiếu bằng chứng phỏng vấn | N11: =Settings!$C$5 -> 4 | P11: Chưa làm | Q11: =IF(OR(P11="Xong",P11="Bỏ"),"",IF(B11<TODAY(),"Quá hạn",IF(B11=TODAY(),"Hôm nay","")))
A12: 9 | B12: =WORKDAY(Settings!$C$4-1,A12,Holidays!$A$5:$A$40) -> 46324 | C12: S01 | D12: =INT((A12-1)/5)+1 -> 2 | E12: =MOD(A12-1,10)+1 -> 9 | F12: P0 · Khởi tạo & Discovery | G12: CSO | H12: =IFERROR(INDEX(Roles!$D$5:$D$26,MATCH(G12,Roles!$A$5:$A$26,0)),"") -> medilens-clinical-safety-officer | I12: Tìm bác sĩ cố vấn (1–2 giờ/tháng); Clinical Risk Management Plan nháp + mẫu hazard log | J12: Recruit a clinical advisor (1–2 h/month); draft Clinical Risk Management Plan + hazard-log template | K12: safety/CRMP.md, hazard-log.xlsx | L12: Cố vấn đồng ý (hoặc có phương án dự phòng); hazard log theo ISO 14971 | N12: =Settings!$C$5 -> 4 | P12: Chưa làm | Q12: =IF(OR(P12="Xong",P12="Bỏ"),"",IF(B12<TODAY(),"Quá hạn",IF(B12=TODAY(),"Hôm nay","")))
A13: 10 | B13: =WORKDAY(Settings!$C$4-1,A13,Holidays!$A$5:$A$40) -> 46325 | C13: S01 | D13: =INT((A13-1)/5)+1 -> 2 | E13: =MOD(A13-1,10)+1 -> 10 | F13: P0 · Khởi tạo & Discovery | G13: PM | H13: =IFERROR(INDEX(Roles!$D$5:$D$26,MATCH(G13,Roles!$A$5:$A$26,0)),"") -> medilens-product-manager | I13: Sprint Review + Retro; cập nhật risk register; buffer cho việc trễ | J13: Sprint review + retro; update risk register; buffer for slipped work | K13: reports/sprint-01.md | L13: Retro có ≥ 1 hành động; rủi ro chấm điểm L×I | N13: =Settings!$C$5 -> 4 | P13: Chưa làm | Q13: =IF(OR(P13="Xong",P13="Bỏ"),"",IF(B13<TODAY(),"Quá hạn",IF(B13=TODAY(),"Hôm nay","")))
A14: 11 | B14: =WORKDAY(Settings!$C$4-1,A14,Holidays!$A$5:$A$40) -> 46328 | C14: S02 | D14: =INT((A14-1)/5)+1 -> 3 | E14: =MOD(A14-1,10)+1 -> 1 | F14: P0 · Khởi tạo & Discovery | G14: BA | H14: =IFERROR(INDEX(Roles!$D$5:$D$26,MATCH(G14,Roles!$A$5:$A$26,0)),"") -> medilens-business-analyst | I14: Planning; problem statement + MoSCoW; khóa MVP 3 Unit: Răng hàm mặt, Tim mạch, Ung bướu | J14: Planning; problem statement + MoSCoW; lock MVP to 3 Units: Dental, Cardiology, Oncology | K14: product/mvp-scope.md | L14: Must ≤ 3 Unit; danh sách Won't ghi rõ | N14: =Settings!$C$5 -> 4 | P14: Chưa làm | Q14: =IF(OR(P14="Xong",P14="Bỏ"),"",IF(B14<TODAY(),"Quá hạn",IF(B14=TODAY(),"Hôm nay","")))
A15: 12 | B15: =WORKDAY(Settings!$C$4-1,A15,Holidays!$A$5:$A$40) -> 46329 | C15: S02 | D15: =INT((A15-1)/5)+1 -> 3 | E15: =MOD(A15-1,10)+1 -> 2 | F15: P0 · Khởi tạo & Discovery | G15: BA | H15: =IFERROR(INDEX(Roles!$D$5:$D$26,MATCH(G15,Roles!$A$5:$A$26,0)),"") -> medilens-business-analyst | I15: BRD v1: quy trình To-Be (BPMN), business rules BR-001…BR-045, glossary VI–EN | J15: BRD v1: To-Be process (BPMN), business rules BR-001…BR-045, VI–EN glossary | K15: docs/BRD-v1.md | L15: Mỗi BR có mã, chủ sở hữu, ý tưởng test | N15: =Settings!$C$5 -> 4 | P15: Chưa làm | Q15: =IF(OR(P15="Xong",P15="Bỏ"),"",IF(B15<TODAY(),"Quá hạn",IF(B15=TODAY(),"Hôm nay","")))
... A22: 19 | B22: =WORKDAY(Settings!$C$4-1,A22,Holidays!$A$5:$A$40) -> 46338 | C22: S02 | D22: =INT((A22-1)/5)+1 -> 4 | E22: =MOD(A22-1,10)+1 -> 9 | F22: P0 · Khởi tạo & Discovery | G22: REG | H22: =IFERROR(INDEX(Roles!$D$5:$D$26,MATCH(G22,Roles!$A$5:$A$26,0)),"") -> medilens-regulatory-privacy-officer | I22: DPIA sơ bộ + kiểm kê dữ liệu; quyết định có cần hồ sơ đánh giá chuyển dữ liệu ra nước ngoài (OTIA) không | J22: Initial DPIA + data inventory; decide whether an outbound transfer impact assessment (OTIA) is needed | K22: privacy/DPIA-v0.md | L22: Mỗi loại dữ liệu có mục đích, cơ sở pháp lý, thời hạn lưu | N22: =Settings!$C$5 -> 4 | P22: Chưa làm | Q22: =IF(OR(P22="Xong",P22="Bỏ"),"",IF(B22<TODAY(),"Quá hạn",IF(B22=TODAY(),"Hôm nay","")))
A23: 20 | B23: =WORKDAY(Settings!$C$4-1,A23,Holidays!$A$5:$A$40) -> 46339 | C23: S02 | D23: =INT((A23-1)/5)+1 -> 4 | E23: =MOD(A23-1,10)+1 -> 10 | F23: P0 · Khởi tạo & Discovery | G23: QC | H23: =IFERROR(INDEX(Roles!$D$5:$D$26,MATCH(G23,Roles!$A$5:$A$26,0)),"") -> medilens-qc-release-gatekeeper | I23: Cổng G0 + G0-R: duyệt Brief, BRD, prototype, Intended Use, RDR; Review + Retro | J23: Gates G0 + G0-R: approve brief, BRD, prototype, intended use, RDR; review + retro | K23: gates/G0.md | L23: Biên bản cổng có người duyệt; không còn blocker | M23: G0, G0-R | N23: =Settings!$C$5 -> 4 | P23: Chưa làm | Q23: =IF(OR(P23="Xong",P23="Bỏ"),"",IF(B23<TODAY(),"Quá hạn",IF(B23=TODAY(),"Hôm nay","")))
A24: 21 | B24: =WORKDAY(Settings!$C$4-1,A24,Holidays!$A$5:$A$40) -> 46342 | C24: S03 | D24: =INT((A24-1)/5)+1 -> 5 | E24: =MOD(A24-1,10)+1 -> 1 | F24: P1 · Foundation | G24: SA | H24: =IFERROR(INDEX(Roles!$D$5:$D$26,MATCH(G24,Roles!$A$5:$A$26,0)),"") -> medilens-solution-architect | I24: Planning; sơ đồ C4 (context, container) + khung SAD arc42 | J24: Planning; C4 context/container diagrams + arc42 SAD skeleton | K24: docs/SAD.md | L24: Sơ đồ có trust boundary và luồng PHI | N24: =Settings!$C$5 -> 4 | P24: Chưa làm | Q24: =IF(OR(P24="Xong",P24="Bỏ"),"",IF(B24<TODAY(),"Quá hạn",IF(B24=TODAY(),"Hôm nay","")))
A25: 22 | B25: =WORKDAY(Settings!$C$4-1,A25,Holidays!$A$5:$A$40) -> 46343 | C25: S03 | D25: =INT((A25-1)/5)+1 -> 5 | E25: =MOD(A25-1,10)+1 -> 2 | F25: P1 · Foundation | G25: OPS | H25: =IFERROR(INDEX(Roles!$D$5:$D$26,MATCH(G25,Roles!$A$5:$A$26,0)),"") -> medilens-cloud-devops-engineer | I25: Monorepo (apps/web, apps/api, apps/worker, infra); pre-commit: lint, format, quét secrets | J25: Monorepo (apps/web, apps/api, apps/worker, infra); pre-commit: lint, format, secret scan | K25: repo | L25: Hook chạy được; README hướng dẫn chạy local | N25: =Settings!$C$5 -> 4 | P25: Chưa làm | Q25: =IF(OR(P25="Xong",P25="Bỏ"),"",IF(B25<TODAY(),"Quá hạn",IF(B25=TODAY(),"Hôm nay","")))
A26: 23 | B26: =WORKDAY(Settings!$C$4-1,A26,Holidays!$A$5:$A$40) -> 46344 | C26: S03 | D26: =INT((A26-1)/5)+1 -> 5 | E26: =MOD(A26-1,10)+1 -> 3 | F26: P1 · Foundation | G26: OPS | H26: =IFERROR(INDEX(Roles!$D$5:$D$26,MATCH(G26,Roles!$A$5:$A$26,0)),"") -> medilens-cloud-devops-engineer | I26: GitHub Actions CI: lint, unit test, SAST (Semgrep), SCA, build image, SBOM | J26: GitHub Actions CI: lint, unit tests, SAST (Semgrep), SCA, image build, SBOM | K26: .github/workflows/ci.yml | L26: CI xanh trên main; chặn High/Critical | N26: =Settings!$C$5 -> 4 | P26: Chưa làm | Q26: =IF(OR(P26="Xong",P26="Bỏ"),"",IF(B26<TODAY(),"Quá hạn",IF(B26=TODAY(),"Hôm nay","")))
A27: 24 | B27: =WORKDAY(Settings!$C$4-1,A27,Holidays!$A$5:$A$40) -> 46345 | C27: S03 | D27: =INT((A27-1)/5)+1 -> 5 | E27: =MOD(A27-1,10)+1 -> 4 | F27: P1 · Foundation | G27: OPS | H27: =IFERROR(INDEX(Roles!$D$5:$D$26,MATCH(G27,Roles!$A$5:$A$26,0)),"") -> medilens-cloud-devops-engineer | I27: AWS Organizations: account management, security, log-archive, nonprod, prod; IAM Identity Center; SCP cơ bản; CloudTrail org trail | J27: AWS Organizations: management, security, log-archive, nonprod, prod accounts; Identity Center; baseline SCPs; org CloudTrail | K27: infra/org | L27: Root có MFA phần cứng; không có IAM user dùng hằng ngày | N27: =Settings!$C$5 -> 4 | P27: Chưa làm | Q27: =IF(OR(P27="Xong",P27="Bỏ"),"",IF(B27<TODAY(),"Quá hạn",IF(B27=TODAY(),"Hôm nay","")))
A28: 25 | B28: =WORKDAY(Settings!$C$4-1,A28,Holidays!$A$5:$A$40) -> 46346 | C28: S03 | D28: =INT((A28-1)/5)+1 -> 5 | E28: =MOD(A28-1,10)+1 -> 5 | F28: P1 · Foundation | G28: OPS | H28: =IFERROR(INDEX(Roles!$D$5:$D$26,MATCH(G28,Roles!$A$5:$A$26,0)),"") -> medilens-cloud-devops-engineer | I28: Terraform VPC nonprod: subnet public/private/worker (worker không route internet), VPC endpoint S3/SQS/KMS/ECR/Logs/Bedrock | J28: Terraform nonprod VPC: public/private/worker subnets (worker with no internet route), VPC endpoints S3/SQS/KMS/ECR/Logs/Bedrock | K28: infra/network | L28: checkov/tfsec không có High; SEC-AR-03 có test | N28: =Settings!$C$5 -> 4 | P28: Chưa làm | Q28: =IF(OR(P28="Xong",P28="Bỏ"),"",IF(B28<TODAY(),"Quá hạn",IF(B28=TODAY(),"Hôm nay","")))
A29: 26 | B29: =WORKDAY(Settings!$C$4-1,A29,Holidays!$A$5:$A$40) -> 46349 | C29: S03 | D29: =INT((A29-1)/5)+1 -> 6 | E29: =MOD(A29-1,10)+1 -> 6 | F29: P1 · Foundation | G29: BE | H29: =IFERROR(INDEX(Roles!$D$5:$D$26,MATCH(G29,Roles!$A$5:$A$26,0)),"") -> medilens-backend-engineer | I29: Khung FastAPI: health check, lỗi dạng Problem Details, OpenAPI, cấu hình theo môi trường | J29: FastAPI skeleton: health check, Problem Details errors, OpenAPI, per-environment config | K29: apps/api | L29: /health trả 200; lỗi không lộ stack trace | N29: =Settings!$C$5 -> 4 | P29: Chưa làm | Q29: =IF(OR(P29="Xong",P29="Bỏ"),"",IF(B29<TODAY(),"Quá hạn",IF(B29=TODAY(),"Hôm nay","")))
A30: 27 | B30: =WORKDAY(Settings!$C$4-1,A30,Holidays!$A$5:$A$40) -> 46351 | C30: S03 | D30: =INT((A30-1)/5)+1 -> 6 | E30: =MOD(A30-1,10)+1 -> 7 | F30: P1 · Foundation | G30: BE | H30: =IFERROR(INDEX(Roles!$D$5:$D$26,MATCH(G30,Roles!$A$5:$A$26,0)),"") -> medilens-backend-engineer | I30: Cognito + OIDC Authorization Code/PKCE, kiểm JWT, cookie HttpOnly/Secure/SameSite | J30: Cognito + OIDC authorization code/PKCE, JWT validation, HttpOnly/Secure/SameSite cookies | K30: auth module | L30: E2E đăng nhập qua; không có token trong localStorage | N30: =Settings!$C$5 -> 4 | P30: Chưa làm | Q30: =IF(OR(P30="Xong",P30="Bỏ"),"",IF(B30<TODAY(),"Quá hạn",IF(B30=TODAY(),"Hôm nay","")))
A31: 28 | B31: =WORKDAY(Settings!$C$4-1,A31,Holidays!$A$5:$A$40) -> 46352 | C31: S03 | D31: =INT((A31-1)/5)+1 -> 6 | E31: =MOD(A31-1,10)+1 -> 8 | F31: P1 · Foundation | G31: FE | H31: =IFERROR(INDEX(Roles!$D$5:$D$26,MATCH(G31,Roles!$A$5:$A$26,0)),"") -> medilens-frontend-engineer | I31: Khung Next.js: layout, next-intl VI/EN, luồng đăng nhập/đăng xuất | J31: Next.js skeleton: layout, next-intl VI/EN, sign-in/sign-out flow | K31: apps/web | L31: Đủ key VI/EN; Lighthouse a11y ≥ 90 | N31: =Settings!$C$5 -> 4 | P31: Chưa làm | Q31: =IF(OR(P31="Xong",P31="Bỏ"),"",IF(B31<TODAY(),"Quá hạn",IF(B31=TODAY(),"Hôm nay","")))
A32: 29 | B32: =WORKDAY(Settings!$C$4-1,A32,Holidays!$A$5:$A$40) -> 46353 | C32: S03 | D32: =INT((A32-1)/5)+1 -> 6 | E32: =MOD(A32-1,10)+1 -> 9 | F32: P1 · Foundation | G32: SEC | H32: =IFERROR(INDEX(Roles!$D$5:$D$26,MATCH(G32,Roles!$A$5:$A$26,0)),"") -> medilens-security-engineer | I32: Threat model STRIDE v1 cho upload, AI, chia sẻ + abuse cases | J32: STRIDE threat model v1 for upload, AI and sharing + abuse cases | K32: security/threat-model.md | L32: Mỗi mối đe dọa có biện pháp và chủ sở hữu | N32: =Settings!$C$5 -> 4 | P32: Chưa làm | Q32: =IF(OR(P32="Xong",P32="Bỏ"),"",IF(B32<TODAY(),"Quá hạn",IF(B32=TODAY(),"Hôm nay","")))
A33: 30 | B33: =WORKDAY(Settings!$C$4-1,A33,Holidays!$A$5:$A$40) -> 46356 | C33: S03 | D33: =INT((A33-1)/5)+1 -> 6 | E33: =MOD(A33-1,10)+1 -> 10 | F33: P1 · Foundation | G33: PM | H33: =IFERROR(INDEX(Roles!$D$5:$D$26,MATCH(G33,Roles!$A$5:$A$26,0)),"") -> medilens-product-manager | I33: Review (video demo ≤ 5 phút) + Retro; buffer | J33: Review (≤ 5-min demo video) + retro; buffer | K33: reports/sprint-03.md | L33: Demo đăng nhập trên nonprod | N33: =Settings!$C$5 -> 4 | P33: Chưa làm | Q33: =IF(OR(P33="Xong",P33="Bỏ"),"",IF(B33<TODAY(),"Quá hạn",IF(B33=TODAY(),"Hôm nay","")))
A34: 31 | B34: =WORKDAY(Settings!$C$4-1,A34,Holidays!$A$5:$A$40) -> 46357 | C34: S04 | D34: =INT((A34-1)/5)+1 -> 7 | E34: =MOD(A34-1,10)+1 -> 1 | F34: P1 · Foundation | G34: BE | H34: =IFERROR(INDEX(Roles!$D$5:$D$26,MATCH(G34,Roles!$A$5:$A$26,0)),"") -> medilens-backend-engineer | I34: Planning; ERD theo domain model (User, PatientProfile, MedicalDocument, Finding, Unit/Region, Consent, AuditEvent) | J34: Planning; ERD from the domain model (User, PatientProfile, MedicalDocument, Finding, Unit/Region, Consent, AuditEvent) | K34: docs/erd | L34: Tên thực thể gần FHIR; review bằng checklist bảo mật | N34: =Settings!$C$5 -> 4 | P34: Chưa làm | Q34: =IF(OR(P34="Xong",P34="Bỏ"),"",IF(B34<TODAY(),"Quá hạn",IF(B34=TODAY(),"Hôm nay","")))
A35: 32 | B35: =WORKDAY(Settings!$C$4-1,A35,Holidays!$A$5:$A$40) -> 46358 | C35: S04 | D35: =INT((A35-1)/5)+1 -> 7 | E35: =MOD(A35-1,10)+1 -> 2 | F35: P1 · Foundation | G35: BE | H35: =IFERROR(INDEX(Roles!$D$5:$D$26,MATCH(G35,Roles!$A$5:$A$26,0)),"") -> medilens-backend-engineer | I35: PostgreSQL 16 + Alembic; schema identity và clinical tách riêng, role DB riêng | J35: PostgreSQL 16 + Alembic; separate identity and clinical schemas and DB roles | K35: migrations/ | L35: Migration up/down chạy trong CI | N35: =Settings!$C$5 -> 4 | P35: Chưa làm | Q35: =IF(OR(P35="Xong",P35="Bỏ"),"",IF(B35<TODAY(),"Quá hạn",IF(B35=TODAY(),"Hôm nay","")))
... A51: 48 | B51: =WORKDAY(Settings!$C$4-1,A51,Holidays!$A$5:$A$40) -> 46380 | C51: S05 | D51: =INT((A51-1)/5)+1 -> 10 | E51: =MOD(A51-1,10)+1 -> 8 | F51: P1 · Foundation | G51: CIN | H51: =IFERROR(INDEX(Roles!$D$5:$D$26,MATCH(G51,Roles!$A$5:$A$26,0)),"") -> medilens-clinical-informaticist | I51: Nạp danh mục mã: ICD-10 (bản Bộ Y tế), tập con LOINC, FDI; ghi license vào register | J51: Load code systems: MoH ICD-10, LOINC subset, FDI; record licences in the register | K51: terminology tables | L51: Loader có test; license đã ghi | N51: =Settings!$C$5 -> 4 | P51: Chưa làm | Q51: =IF(OR(P51="Xong",P51="Bỏ"),"",IF(B51<TODAY(),"Quá hạn",IF(B51=TODAY(),"Hôm nay","")))
A52: 49 | B52: =WORKDAY(Settings!$C$4-1,A52,Holidays!$A$5:$A$40) -> 46381 | C52: S05 | D52: =INT((A52-1)/5)+1 -> 10 | E52: =MOD(A52-1,10)+1 -> 9 | F52: P1 · Foundation | G52: DC | H52: =IFERROR(INDEX(Roles!$D$5:$D$26,MATCH(G52,Roles!$A$5:$A$26,0)),"") -> medilens-data-curator | I52: G1-D lần 1 cho dữ liệu đánh giá & synthetic: Dataset Card, checksum, kiểm trùng hash giữa các tập | J52: G1-D round 1 for evaluation & synthetic data: Dataset Card, checksum, hash-based leakage check | K52: datasets/cards | L52: Checklist 25.6 đạt cho dữ liệu đánh giá | M52: G1-D | N52: =Settings!$C$5 -> 4 | P52: Chưa làm | Q52: =IF(OR(P52="Xong",P52="Bỏ"),"",IF(B52<TODAY(),"Quá hạn",IF(B52=TODAY(),"Hôm nay","")))
A53: 50 | B53: =WORKDAY(Settings!$C$4-1,A53,Holidays!$A$5:$A$40) -> 46384 | C53: S05 | D53: =INT((A53-1)/5)+1 -> 10 | E53: =MOD(A53-1,10)+1 -> 10 | F53: P1 · Foundation | G53: QC | H53: =IFERROR(INDEX(Roles!$D$5:$D$26,MATCH(G53,Roles!$A$5:$A$26,0)),"") -> medilens-qc-release-gatekeeper | I53: Cổng G1: ADR chốt, CI xanh, 1 tài liệu chạy trọn pipeline trên staging; Review + Retro | J53: Gate G1: ADRs final, CI green, one document end-to-end on staging; review + retro | K53: gates/G1.md | L53: Có bằng chứng E2E trên staging | M53: G1 | N53: =Settings!$C$5 -> 4 | P53: Chưa làm | Q53: =IF(OR(P53="Xong",P53="Bỏ"),"",IF(B53<TODAY(),"Quá hạn",IF(B53=TODAY(),"Hôm nay","")))
A54: 51 | B54: =WORKDAY(Settings!$C$4-1,A54,Holidays!$A$5:$A$40) -> 46385 | C54: S06 | D54: =INT((A54-1)/5)+1 -> 11 | E54: =MOD(A54-1,10)+1 -> 1 | F54: P2 · Build MVP | G54: BA | H54: =IFERROR(INDEX(Roles!$D$5:$D$26,MATCH(G54,Roles!$A$5:$A$26,0)),"") -> medilens-business-analyst | I54: Planning; user story + Gherkin cho upload, tiến trình, lỗi chụp lại | J54: Planning; user stories + Gherkin for upload, progress and retake errors | K54: backlog | L54: Story ≤ 3 ngày, đạt INVEST | N54: =Settings!$C$5 -> 4 | P54: Chưa làm | Q54: =IF(OR(P54="Xong",P54="Bỏ"),"",IF(B54<TODAY(),"Quá hạn",IF(B54=TODAY(),"Hôm nay","")))
A55: 52 | B55: =WORKDAY(Settings!$C$4-1,A55,Holidays!$A$5:$A$40) -> 46386 | C55: S06 | D55: =INT((A55-1)/5)+1 -> 11 | E55: =MOD(A55-1,10)+1 -> 2 | F55: P2 · Build MVP | G55: FE | H55: =IFERROR(INDEX(Roles!$D$5:$D$26,MATCH(G55,Roles!$A$5:$A$26,0)),"") -> medilens-frontend-engineer | I55: Màn Upload: chụp/chọn ảnh, nhiều trang, hướng dẫn chụp, kiểm kích thước phía client | J55: Upload screen: capture/select, multi-page, capture tips, client-side size check | K55: upload page | L55: Chạy trên mobile và desktop; có nhãn a11y | N55: =Settings!$C$5 -> 4 | P55: Chưa làm | Q55: =IF(OR(P55="Xong",P55="Bỏ"),"",IF(B55<TODAY(),"Quá hạn",IF(B55=TODAY(),"Hôm nay","")))
A56: 53 | B56: =WORKDAY(Settings!$C$4-1,A56,Holidays!$A$5:$A$40) -> 46387 | C56: S06 | D56: =INT((A56-1)/5)+1 -> 11 | E56: =MOD(A56-1,10)+1 -> 3 | F56: P2 · Build MVP | G56: BE | H56: =IFERROR(INDEX(Roles!$D$5:$D$26,MATCH(G56,Roles!$A$5:$A$26,0)),"") -> medilens-backend-engineer | I56: API trạng thái + SSE realtime; outbox pattern cho domain event | J56: Status API + SSE realtime; outbox pattern for domain events | K56: status endpoints | L56: Cập nhật trạng thái < 2 giây | N56: =Settings!$C$5 -> 4 | P56: Chưa làm | Q56: =IF(OR(P56="Xong",P56="Bỏ"),"",IF(B56<TODAY(),"Quá hạn",IF(B56=TODAY(),"Hôm nay","")))
A57: 54 | B57: =WORKDAY(Settings!$C$4-1,A57,Holidays!$A$5:$A$40) -> 46391 | C57: S06 | D57: =INT((A57-1)/5)+1 -> 11 | E57: =MOD(A57-1,10)+1 -> 4 | F57: P2 · Build MVP | G57: AI | H57: =IFERROR(INDEX(Roles!$D$5:$D$26,MATCH(G57,Roles!$A$5:$A$26,0)),"") -> medilens-ai-ml-engineer | I57: Phân loại trang: rule + LLM Tier S zero-shot (9 loại phiếu) | J57: Page classification: rules + Tier-S LLM zero-shot (9 page types) | K57: classifier step | L57: Accuracy ≥ 0,90 trên golden set | N57: =Settings!$C$5 -> 4 | P57: Chưa làm | Q57: =IF(OR(P57="Xong",P57="Bỏ"),"",IF(B57<TODAY(),"Quá hạn",IF(B57=TODAY(),"Hôm nay","")))
A58: 55 | B58: =WORKDAY(Settings!$C$4-1,A58,Holidays!$A$5:$A$40) -> 46392 | C58: S06 | D58: =INT((A58-1)/5)+1 -> 11 | E58: =MOD(A58-1,10)+1 -> 5 | F58: P2 · Build MVP | G58: AI | H58: =IFERROR(INDEX(Roles!$D$5:$D$26,MATCH(G58,Roles!$A$5:$A$26,0)),"") -> medilens-ai-ml-engineer | I58: Cải thiện OCR: phát hiện viền tài liệu, perspective transform, VietOCR cho dòng chữ in | J58: OCR improvements: document edge detection, perspective transform, VietOCR for printed lines | K58: ocr v2 | L58: CER giảm so với baseline S02 | N58: =Settings!$C$5 -> 4 | P58: Chưa làm | Q58: =IF(OR(P58="Xong",P58="Bỏ"),"",IF(B58<TODAY(),"Quá hạn",IF(B58=TODAY(),"Hôm nay","")))
A59: 56 | B59: =WORKDAY(Settings!$C$4-1,A59,Holidays!$A$5:$A$40) -> 46393 | C59: S06 | D59: =INT((A59-1)/5)+1 -> 12 | E59: =MOD(A59-1,10)+1 -> 6 | F59: P2 · Build MVP | G59: FE | H59: =IFERROR(INDEX(Roles!$D$5:$D$26,MATCH(G59,Roles!$A$5:$A$26,0)),"") -> medilens-frontend-engineer | I59: Màn tiến trình + thông báo lỗi thân thiện (ảnh mờ → hướng dẫn chụp lại) | J59: Progress screen + friendly errors (blurry → retake guidance) | K59: UI states | L59: Mỗi lỗi có hành động tiếp theo | N59: =Settings!$C$5 -> 4 | P59: Chưa làm | Q59: =IF(OR(P59="Xong",P59="Bỏ"),"",IF(B59<TODAY(),"Quá hạn",IF(B59=TODAY(),"Hôm nay","")))
A60: 57 | B60: =WORKDAY(Settings!$C$4-1,A60,Holidays!$A$5:$A$40) -> 46394 | C60: S06 | D60: =INT((A60-1)/5)+1 -> 12 | E60: =MOD(A60-1,10)+1 -> 7 | F60: P2 · Build MVP | G60: QA | H60: =IFERROR(INDEX(Roles!$D$5:$D$26,MATCH(G60,Roles!$A$5:$A$26,0)),"") -> medilens-qa-engineer | I60: Test API + contract test upload; bộ file độc (EICAR, PDF chứa JS, polyglot) | J60: API + contract tests for upload; malicious file set (EICAR, JS-PDF, polyglot) | K60: tests/upload | L60: File độc bị chặn trong CI | N60: =Settings!$C$5 -> 4 | P60: Chưa làm | Q60: =IF(OR(P60="Xong",P60="Bỏ"),"",IF(B60<TODAY(),"Quá hạn",IF(B60=TODAY(),"Hôm nay","")))
A61: 58 | B61: =WORKDAY(Settings!$C$4-1,A61,Holidays!$A$5:$A$40) -> 46395 | C61: S06 | D61: =INT((A61-1)/5)+1 -> 12 | E61: =MOD(A61-1,10)+1 -> 8 | F61: P2 · Build MVP | G61: SEC | H61: =IFERROR(INDEX(Roles!$D$5:$D$26,MATCH(G61,Roles!$A$5:$A$26,0)),"") -> medilens-security-engineer | I61: Rà soát upload theo SEC-AP-07; chạy scan_log_for_pii.py trên log staging | J61: Review upload against SEC-AP-07; run scan_log_for_pii.py on staging logs | K61: security review note | L61: 0 PII trong log | N61: =Settings!$C$5 -> 4 | P61: Chưa làm | Q61: =IF(OR(P61="Xong",P61="Bỏ"),"",IF(B61<TODAY(),"Quá hạn",IF(B61=TODAY(),"Hôm nay","")))
A62: 59 | B62: =WORKDAY(Settings!$C$4-1,A62,Holidays!$A$5:$A$40) -> 46398 | C62: S06 | D62: =INT((A62-1)/5)+1 -> 12 | E62: =MOD(A62-1,10)+1 -> 9 | F62: P2 · Build MVP | G62: TW | H62: =IFERROR(INDEX(Roles!$D$5:$D$26,MATCH(G62,Roles!$A$5:$A$26,0)),"") -> medilens-technical-writer | I62: Hướng dẫn chụp bệnh án VI/EN + glossary thuật ngữ ban đầu | J62: VI/EN capture guide + initial terminology glossary | K62: docs/user/capture-guide | L62: Ngôn ngữ đơn giản, đã đọc soát | N62: =Settings!$C$5 -> 4 | P62: Chưa làm | Q62: =IF(OR(P62="Xong",P62="Bỏ"),"",IF(B62<TODAY(),"Quá hạn",IF(B62=TODAY(),"Hôm nay","")))
A63: 60 | B63: =WORKDAY(Settings!$C$4-1,A63,Holidays!$A$5:$A$40) -> 46399 | C63: S06 | D63: =INT((A63-1)/5)+1 -> 12 | E63: =MOD(A63-1,10)+1 -> 10 | F63: P2 · Build MVP | G63: PM | H63: =IFERROR(INDEX(Roles!$D$5:$D$26,MATCH(G63,Roles!$A$5:$A$26,0)),"") -> medilens-product-manager | I63: Review: demo upload → OCR realtime; Retro; buffer | J63: Review: demo upload → realtime OCR; retro; buffer | K63: reports/sprint-06.md | L63: Demo được ghi hình | N63: =Settings!$C$5 -> 4 | P63: Chưa làm | Q63: =IF(OR(P63="Xong",P63="Bỏ"),"",IF(B63<TODAY(),"Quá hạn",IF(B63=TODAY(),"Hôm nay","")))
A64: 61 | B64: =WORKDAY(Settings!$C$4-1,A64,Holidays!$A$5:$A$40) -> 46400 | C64: S07 | D64: =INT((A64-1)/5)+1 -> 13 | E64: =MOD(A64-1,10)+1 -> 1 | F64: P2 · Build MVP | G64: AI | H64: =IFERROR(INDEX(Roles!$D$5:$D$26,MATCH(G64,Roles!$A$5:$A$26,0)),"") -> medilens-ai-ml-engineer | I64: Planning; prompt v2 few-shot theo Unit; mỗi trường có trích dẫn + bbox + độ tin cậy | J64: Planning; prompt v2 few-shot per Unit; every field has citation + bbox + confidence | K64: prompts/extract-v2 | L64: Mọi trường có nguồn trích dẫn | N64: =Settings!$C$5 -> 4 | P64: Chưa làm | Q64: =IF(OR(P64="Xong",P64="Bỏ"),"",IF(B64<TODAY(),"Quá hạn",IF(B64=TODAY(),"Hôm nay","")))
A65: 62 | B65: =WORKDAY(Settings!$C$4-1,A65,Holidays!$A$5:$A$40) -> 46401 | C65: S07 | D65: =INT((A65-1)/5)+1 -> 13 | E65: =MOD(A65-1,10)+1 -> 2 | F65: P2 · Build MVP | G65: AI | H65: =IFERROR(INDEX(Roles!$D$5:$D$26,MATCH(G65,Roles!$A$5:$A$26,0)),"") -> medilens-ai-ml-engineer | I65: Chuẩn hóa: viết tắt → đầy đủ; map ICD-10/LOINC bằng từ điển + embedding + rerank | J65: Normalisation: abbreviations → full terms; ICD-10/LOINC mapping via dictionary + embeddings + rerank | K65: normaliser | L65: Đo top-1 accuracy mã; báo cáo lỗi thường gặp | N65: =Settings!$C$5 -> 4 | P65: Chưa làm | Q65: =IF(OR(P65="Xong",P65="Bỏ"),"",IF(B65<TODAY(),"Quá hạn",IF(B65=TODAY(),"Hôm nay","")))
... A112: 109 | B112: =WORKDAY(Settings!$C$4-1,A112,Holidays!$A$5:$A$40) -> 46475 | C112: S11 | D112: =INT((A112-1)/5)+1 -> 22 | E112: =MOD(A112-1,10)+1 -> 9 | F112: P2 · Build MVP | G112: TW | H112: =IFERROR(INDEX(Roles!$D$5:$D$26,MATCH(G112,Roles!$A$5:$A$26,0)),"") -> medilens-technical-writer | I112: Hướng dẫn sử dụng nháp + release notes nội bộ | J112: Draft user guide + internal release notes | K112: docs/user-guide-draft | L112: Đủ các luồng Must | N112: =Settings!$C$5 -> 4 | P112: Chưa làm | Q112: =IF(OR(P112="Xong",P112="Bỏ"),"",IF(B112<TODAY(),"Quá hạn",IF(B112=TODAY(),"Hôm nay","")))
A113: 110 | B113: =WORKDAY(Settings!$C$4-1,A113,Holidays!$A$5:$A$40) -> 46476 | C113: S11 | D113: =INT((A113-1)/5)+1 -> 22 | E113: =MOD(A113-1,10)+1 -> 10 | F113: P2 · Build MVP | G113: QC | H113: =IFERROR(INDEX(Roles!$D$5:$D$26,MATCH(G113,Roles!$A$5:$A$26,0)),"") -> medilens-qc-release-gatekeeper | I113: Cổng G2 feature complete; Review + Retro | J113: Gate G2 feature complete; review + retro | K113: gates/G2.md | L113: Mọi Must xong, metric đạt | M113: G2 | N113: =Settings!$C$5 -> 4 | P113: Chưa làm | Q113: =IF(OR(P113="Xong",P113="Bỏ"),"",IF(B113<TODAY(),"Quá hạn",IF(B113=TODAY(),"Hôm nay","")))
A114: 111 | B114: =WORKDAY(Settings!$C$4-1,A114,Holidays!$A$5:$A$40) -> 46477 | C114: S12 | D114: =INT((A114-1)/5)+1 -> 23 | E114: =MOD(A114-1,10)+1 -> 1 | F114: P3 · Hardening | G114: SEC | H114: =IFERROR(INDEX(Roles!$D$5:$D$26,MATCH(G114,Roles!$A$5:$A$26,0)),"") -> medilens-security-engineer | I114: Planning; checklist Security Evidence Pack (ASVS L2 → bằng chứng) | J114: Planning; Security Evidence Pack checklist (ASVS L2 → evidence) | K114: security/evidence-pack.md | L114: Mọi SEC MUST có bằng chứng dự kiến | N114: =Settings!$C$5 -> 4 | P114: Chưa làm | Q114: =IF(OR(P114="Xong",P114="Bỏ"),"",IF(B114<TODAY(),"Quá hạn",IF(B114=TODAY(),"Hôm nay","")))
A115: 112 | B115: =WORKDAY(Settings!$C$4-1,A115,Holidays!$A$5:$A$40) -> 46478 | C115: S12 | D115: =INT((A115-1)/5)+1 -> 23 | E115: =MOD(A115-1,10)+1 -> 2 | F115: P3 · Hardening | G115: OPS | H115: =IFERROR(INDEX(Roles!$D$5:$D$26,MATCH(G115,Roles!$A$5:$A$26,0)),"") -> medilens-cloud-devops-engineer | I115: Tách PHI Service + AI Gateway thành ECS service riêng, IAM role riêng (mức B); deny bedrock:InvokeModel* cho role khác | J115: Split PHI Service + AI Gateway into separate ECS services with own IAM roles (level B); deny bedrock:InvokeModel* elsewhere | K115: infra/services | L115: Test SEC-AR-01, SEC-AR-04 qua | N115: =Settings!$C$5 -> 4 | P115: Chưa làm | Q115: =IF(OR(P115="Xong",P115="Bỏ"),"",IF(B115<TODAY(),"Quá hạn",IF(B115=TODAY(),"Hôm nay","")))
A116: 113 | B116: =WORKDAY(Settings!$C$4-1,A116,Holidays!$A$5:$A$40) -> 46479 | C116: S12 | D116: =INT((A116-1)/5)+1 -> 23 | E116: =MOD(A116-1,10)+1 -> 3 | F116: P3 · Hardening | G116: BE | H116: =IFERROR(INDEX(Roles!$D$5:$D$26,MATCH(G116,Roles!$A$5:$A$26,0)),"") -> medilens-backend-engineer | I116: DEK theo hồ sơ (envelope encryption) + crypto-shredding | J116: Per-record DEK (envelope encryption) + crypto-shredding | K116: crypto module | L116: Hồ sơ đã xóa không đọc được kể cả từ backup thử | N116: =Settings!$C$5 -> 4 | P116: Chưa làm | Q116: =IF(OR(P116="Xong",P116="Bỏ"),"",IF(B116<TODAY(),"Quá hạn",IF(B116=TODAY(),"Hôm nay","")))
A117: 114 | B117: =WORKDAY(Settings!$C$4-1,A117,Holidays!$A$5:$A$40) -> 46482 | C117: S12 | D117: =INT((A117-1)/5)+1 -> 23 | E117: =MOD(A117-1,10)+1 -> 4 | F117: P3 · Hardening | G117: SEC | H117: =IFERROR(INDEX(Roles!$D$5:$D$26,MATCH(G117,Roles!$A$5:$A$26,0)),"") -> medilens-security-engineer | I117: Audit log chuỗi hash + job kiểm toàn vẹn hằng ngày (SEC-AR-05) | J117: Hash-chained audit log + daily integrity job (SEC-AR-05) | K117: audit job | L117: Test sửa log bị phát hiện | N117: =Settings!$C$5 -> 4 | P117: Chưa làm | Q117: =IF(OR(P117="Xong",P117="Bỏ"),"",IF(B117<TODAY(),"Quá hạn",IF(B117=TODAY(),"Hôm nay","")))
A118: 115 | B118: =WORKDAY(Settings!$C$4-1,A118,Holidays!$A$5:$A$40) -> 46483 | C118: S12 | D118: =INT((A118-1)/5)+1 -> 23 | E118: =MOD(A118-1,10)+1 -> 5 | F118: P3 · Hardening | G118: OPS | H118: =IFERROR(INDEX(Roles!$D$5:$D$26,MATCH(G118,Roles!$A$5:$A$26,0)),"") -> medilens-cloud-devops-engineer | I118: WAF managed rules + rate rule; Security Hub/Config ≥ 90% | J118: WAF managed rules + rate rule; Security Hub/Config ≥ 90% | K118: infra/edge | L118: Điểm Security Hub ≥ 90% | N118: =Settings!$C$5 -> 4 | P118: Chưa làm | Q118: =IF(OR(P118="Xong",P118="Bỏ"),"",IF(B118<TODAY(),"Quá hạn",IF(B118=TODAY(),"Hôm nay","")))
A119: 116 | B119: =WORKDAY(Settings!$C$4-1,A119,Holidays!$A$5:$A$40) -> 46484 | C119: S12 | D119: =INT((A119-1)/5)+1 -> 24 | E119: =MOD(A119-1,10)+1 -> 6 | F119: P3 · Hardening | G119: QA | H119: =IFERROR(INDEX(Roles!$D$5:$D$26,MATCH(G119,Roles!$A$5:$A$26,0)),"") -> medilens-qa-engineer | I119: Load test k6 (NFR-02/03/04) | J119: k6 load test (NFR-02/03/04) | K119: perf report | L119: p95 đọc ≤ 300 ms; 95% tài liệu < 2 phút | N119: =Settings!$C$5 -> 4 | P119: Chưa làm | Q119: =IF(OR(P119="Xong",P119="Bỏ"),"",IF(B119<TODAY(),"Quá hạn",IF(B119=TODAY(),"Hôm nay","")))
A120: 117 | B120: =WORKDAY(Settings!$C$4-1,A120,Holidays!$A$5:$A$40) -> 46485 | C120: S12 | D120: =INT((A120-1)/5)+1 -> 24 | E120: =MOD(A120-1,10)+1 -> 7 | F120: P3 · Hardening | G120: SEC | H120: =IFERROR(INDEX(Roles!$D$5:$D$26,MATCH(G120,Roles!$A$5:$A$26,0)),"") -> medilens-security-engineer | I120: DAST ZAP trên staging + fuzz API (schemathesis) | J120: ZAP DAST on staging + API fuzzing (schemathesis) | K120: DAST report | L120: 0 High | N120: =Settings!$C$5 -> 4 | P120: Chưa làm | Q120: =IF(OR(P120="Xong",P120="Bỏ"),"",IF(B120<TODAY(),"Quá hạn",IF(B120=TODAY(),"Hôm nay","")))
A121: 118 | B121: =WORKDAY(Settings!$C$4-1,A121,Holidays!$A$5:$A$40) -> 46486 | C121: S12 | D121: =INT((A121-1)/5)+1 -> 24 | E121: =MOD(A121-1,10)+1 -> 8 | F121: P3 · Hardening | G121: FE | H121: =IFERROR(INDEX(Roles!$D$5:$D$26,MATCH(G121,Roles!$A$5:$A$26,0)),"") -> medilens-frontend-engineer | I121: Audit WCAG 2.2 AA: bàn phím, trình đọc màn hình, tương phản | J121: WCAG 2.2 AA audit: keyboard, screen reader, contrast | K121: a11y report | L121: 0 lỗi nghiêm trọng | N121: =Settings!$C$5 -> 4 | P121: Chưa làm | Q121: =IF(OR(P121="Xong",P121="Bỏ"),"",IF(B121<TODAY(),"Quá hạn",IF(B121=TODAY(),"Hôm nay","")))
A122: 119 | B122: =WORKDAY(Settings!$C$4-1,A122,Holidays!$A$5:$A$40) -> 46489 | C122: S12 | D122: =INT((A122-1)/5)+1 -> 24 | E122: =MOD(A122-1,10)+1 -> 9 | F122: P3 · Hardening | G122: SRE | H122: =IFERROR(INDEX(Roles!$D$5:$D$26,MATCH(G122,Roles!$A$5:$A$26,0)),"") -> medilens-sre-operations | I122: SLO + alarm + runbook cho mỗi alarm; dashboard vận hành | J122: SLOs + alarms + a runbook per alarm; ops dashboard | K122: runbooks/ | L122: Mọi alarm có runbook | N122: =Settings!$C$5 -> 4 | P122: Chưa làm | Q122: =IF(OR(P122="Xong",P122="Bỏ"),"",IF(B122<TODAY(),"Quá hạn",IF(B122=TODAY(),"Hôm nay","")))
A123: 120 | B123: =WORKDAY(Settings!$C$4-1,A123,Holidays!$A$5:$A$40) -> 46490 | C123: S12 | D123: =INT((A123-1)/5)+1 -> 24 | E123: =MOD(A123-1,10)+1 -> 10 | F123: P3 · Hardening | G123: PM | H123: =IFERROR(INDEX(Roles!$D$5:$D$26,MATCH(G123,Roles!$A$5:$A$26,0)),"") -> medilens-product-manager | I123: Review + Retro; cập nhật risk register; buffer | J123: Review + retro; update risk register; buffer | K123: reports/sprint-12.md | L123: Rủi ro đỏ có hành động | N123: =Settings!$C$5 -> 4 | P123: Chưa làm | Q123: =IF(OR(P123="Xong",P123="Bỏ"),"",IF(B123<TODAY(),"Quá hạn",IF(B123=TODAY(),"Hôm nay","")))
A124: 121 | B124: =WORKDAY(Settings!$C$4-1,A124,Holidays!$A$5:$A$40) -> 46491 | C124: S13 | D124: =INT((A124-1)/5)+1 -> 25 | E124: =MOD(A124-1,10)+1 -> 1 | F124: P3 · Hardening | G124: CSO | H124: =IFERROR(INDEX(Roles!$D$5:$D$26,MATCH(G124,Roles!$A$5:$A$26,0)),"") -> medilens-clinical-safety-officer | I124: Planning; protocol xác thực lâm sàng: 2 bác sĩ × 100 hồ sơ synthetic | J124: Planning; clinical validation protocol: 2 clinicians × 100 synthetic records | K124: safety/validation-protocol.md | L124: Protocol được duyệt | N124: =Settings!$C$5 -> 4 | P124: Chưa làm | Q124: =IF(OR(P124="Xong",P124="Bỏ"),"",IF(B124<TODAY(),"Quá hạn",IF(B124=TODAY(),"Hôm nay","")))
A125: 122 | B125: =WORKDAY(Settings!$C$4-1,A125,Holidays!$A$5:$A$40) -> 46492 | C125: S13 | D125: =INT((A125-1)/5)+1 -> 25 | E125: =MOD(A125-1,10)+1 -> 2 | F125: P3 · Hardening | G125: CSO | H125: =IFERROR(INDEX(Roles!$D$5:$D$26,MATCH(G125,Roles!$A$5:$A$26,0)),"") -> medilens-clinical-safety-officer | I125: Chạy xác thực; đo mức đồng thuận (kappa) về mapping và nội dung | J125: Run validation; measure agreement (kappa) on mapping and content | K125: validation results | L125: Kappa và danh sách bất đồng được ghi | N125: =Settings!$C$5 -> 4 | P125: Chưa làm | Q125: =IF(OR(P125="Xong",P125="Bỏ"),"",IF(B125<TODAY(),"Quá hạn",IF(B125=TODAY(),"Hôm nay","")))
... A132: 129 | B132: =WORKDAY(Settings!$C$4-1,A132,Holidays!$A$5:$A$40) -> 46504 | C132: S13 | D132: =INT((A132-1)/5)+1 -> 26 | E132: =MOD(A132-1,10)+1 -> 9 | F132: P3 · Hardening | G132: SRE | H132: =IFERROR(INDEX(Roles!$D$5:$D$26,MATCH(G132,Roles!$A$5:$A$26,0)),"") -> medilens-sre-operations | I132: DR drill: khôi phục RDS PITR + S3 version; đo RTO/RPO | J132: DR drill: restore RDS PITR + S3 versions; measure RTO/RPO | K132: sre/dr-drill-1.md | L132: RTO ≤ 4 giờ | N132: =Settings!$C$5 -> 4 | P132: Chưa làm | Q132: =IF(OR(P132="Xong",P132="Bỏ"),"",IF(B132<TODAY(),"Quá hạn",IF(B132=TODAY(),"Hôm nay","")))
A133: 130 | B133: =WORKDAY(Settings!$C$4-1,A133,Holidays!$A$5:$A$40) -> 46505 | C133: S13 | D133: =INT((A133-1)/5)+1 -> 26 | E133: =MOD(A133-1,10)+1 -> 10 | F133: P3 · Hardening | G133: QC | H133: =IFERROR(INDEX(Roles!$D$5:$D$26,MATCH(G133,Roles!$A$5:$A$26,0)),"") -> medilens-qc-release-gatekeeper | I133: Cổng G2-CS; Review + Retro | J133: Gate G2-CS; review + retro | K133: gates/G2-CS.md | L133: Safety Case đã ký | M133: G2-CS | N133: =Settings!$C$5 -> 4 | P133: Chưa làm | Q133: =IF(OR(P133="Xong",P133="Bỏ"),"",IF(B133<TODAY(),"Quá hạn",IF(B133=TODAY(),"Hôm nay","")))
A134: 131 | B134: =WORKDAY(Settings!$C$4-1,A134,Holidays!$A$5:$A$40) -> 46506 | C134: S14 | D134: =INT((A134-1)/5)+1 -> 27 | E134: =MOD(A134-1,10)+1 -> 1 | F134: P3 · Hardening | G134: SEC | H134: =IFERROR(INDEX(Roles!$D$5:$D$26,MATCH(G134,Roles!$A$5:$A$26,0)),"") -> medilens-security-engineer | I134: Planning; phạm vi + rules of engagement cho pentest bên ngoài | J134: Planning; scope + rules of engagement for external pentest | K134: security/pentest-RoE.md | L134: RoE được ký | N134: =Settings!$C$5 -> 4 | P134: Chưa làm | Q134: =IF(OR(P134="Xong",P134="Bỏ"),"",IF(B134<TODAY(),"Quá hạn",IF(B134=TODAY(),"Hôm nay","")))
A135: 132 | B135: =WORKDAY(Settings!$C$4-1,A135,Holidays!$A$5:$A$40) -> 46510 | C135: S14 | D135: =INT((A135-1)/5)+1 -> 27 | E135: =MOD(A135-1,10)+1 -> 2 | F135: P3 · Hardening | G135: SEC | H135: =IFERROR(INDEX(Roles!$D$5:$D$26,MATCH(G135,Roles!$A$5:$A$26,0)),"") -> medilens-security-engineer | I135: Hỗ trợ pentest; công bố security.txt + chính sách công bố lỗ hổng (VDP) | J135: Support the pentest; publish security.txt + vulnerability disclosure policy (VDP) | K135: security.txt, VDP | L135: Đã công bố | N135: =Settings!$C$5 -> 4 | P135: Chưa làm | Q135: =IF(OR(P135="Xong",P135="Bỏ"),"",IF(B135<TODAY(),"Quá hạn",IF(B135=TODAY(),"Hôm nay","")))
A136: 133 | B136: =WORKDAY(Settings!$C$4-1,A136,Holidays!$A$5:$A$40) -> 46511 | C136: S14 | D136: =INT((A136-1)/5)+1 -> 27 | E136: =MOD(A136-1,10)+1 -> 3 | F136: P3 · Hardening | G136: BE | H136: =IFERROR(INDEX(Roles!$D$5:$D$26,MATCH(G136,Roles!$A$5:$A$26,0)),"") -> medilens-backend-engineer | I136: Sửa finding High/Medium + retest | J136: Fix High/Medium findings + retest | K136: fix PRs | L136: Retest qua | N136: =Settings!$C$5 -> 4 | P136: Chưa làm | Q136: =IF(OR(P136="Xong",P136="Bỏ"),"",IF(B136<TODAY(),"Quá hạn",IF(B136=TODAY(),"Hôm nay","")))
A137: 134 | B137: =WORKDAY(Settings!$C$4-1,A137,Holidays!$A$5:$A$40) -> 46512 | C137: S14 | D137: =INT((A137-1)/5)+1 -> 27 | E137: =MOD(A137-1,10)+1 -> 4 | F137: P3 · Hardening | G137: AI | H137: =IFERROR(INDEX(Roles!$D$5:$D$26,MATCH(G137,Roles!$A$5:$A$26,0)),"") -> medilens-ai-ml-engineer | I137: Kiểm thiên lệch theo nhóm (chữ tay/in, ảnh tốt/xấu, VI/EN) + calibration (ECE) | J137: Bias check by stratum (handwritten/printed, good/bad photo, VI/EN) + calibration (ECE) | K137: ai/fairness-report.md | L137: Chênh lệch giữa nhóm trong ngưỡng | N137: =Settings!$C$5 -> 4 | P137: Chưa làm | Q137: =IF(OR(P137="Xong",P137="Bỏ"),"",IF(B137<TODAY(),"Quá hạn",IF(B137=TODAY(),"Hôm nay","")))
A138: 135 | B138: =WORKDAY(Settings!$C$4-1,A138,Holidays!$A$5:$A$40) -> 46513 | C138: S14 | D138: =INT((A138-1)/5)+1 -> 27 | E138: =MOD(A138-1,10)+1 -> 5 | F138: P3 · Hardening | G138: QA | H138: =IFERROR(INDEX(Roles!$D$5:$D$26,MATCH(G138,Roles!$A$5:$A$26,0)),"") -> medilens-qa-engineer | I138: UAT script + UAT với 3–5 người | J138: UAT script + UAT with 3–5 people | K138: qa/uat.md | L138: Pass rate ≥ 90% | N138: =Settings!$C$5 -> 4 | P138: Chưa làm | Q138: =IF(OR(P138="Xong",P138="Bỏ"),"",IF(B138<TODAY(),"Quá hạn",IF(B138=TODAY(),"Hôm nay","")))
A139: 136 | B139: =WORKDAY(Settings!$C$4-1,A139,Holidays!$A$5:$A$40) -> 46514 | C139: S14 | D139: =INT((A139-1)/5)+1 -> 28 | E139: =MOD(A139-1,10)+1 -> 6 | F139: P3 · Hardening | G139: TW | H139: =IFERROR(INDEX(Roles!$D$5:$D$26,MATCH(G139,Roles!$A$5:$A$26,0)),"") -> medilens-technical-writer | I139: User guide, FAQ, tài liệu API VI/EN hoàn chỉnh | J139: Complete VI/EN user guide, FAQ, API docs | K139: docs/ | L139: Thuật ngữ khớp glossary | N139: =Settings!$C$5 -> 4 | P139: Chưa làm | Q139: =IF(OR(P139="Xong",P139="Bỏ"),"",IF(B139<TODAY(),"Quá hạn",IF(B139=TODAY(),"Hôm nay","")))
A140: 137 | B140: =WORKDAY(Settings!$C$4-1,A140,Holidays!$A$5:$A$40) -> 46517 | C140: S14 | D140: =INT((A140-1)/5)+1 -> 28 | E140: =MOD(A140-1,10)+1 -> 7 | F140: P3 · Hardening | G140: SUP | H140: =IFERROR(INDEX(Roles!$D$5:$D$26,MATCH(G140,Roles!$A$5:$A$26,0)),"") -> medilens-support-success | I140: Mô hình hỗ trợ L1/L2/L3, kênh, SLA phản hồi, knowledge base | J140: Support model L1/L2/L3, channels, response SLA, knowledge base | K140: support/plan.md | L140: Phản hồi an toàn lâm sàng chuyển CSO | N140: =Settings!$C$5 -> 4 | P140: Chưa làm | Q140: =IF(OR(P140="Xong",P140="Bỏ"),"",IF(B140<TODAY(),"Quá hạn",IF(B140=TODAY(),"Hôm nay","")))
A141: 138 | B141: =WORKDAY(Settings!$C$4-1,A141,Holidays!$A$5:$A$40) -> 46518 | C141: S14 | D141: =INT((A141-1)/5)+1 -> 28 | E141: =MOD(A141-1,10)+1 -> 8 | F141: P3 · Hardening | G141: OPS | H141: =IFERROR(INDEX(Roles!$D$5:$D$26,MATCH(G141,Roles!$A$5:$A$26,0)),"") -> medilens-cloud-devops-engineer | I141: Prod bằng Terraform; blue/green; test rollback | J141: Prod via Terraform; blue/green; rollback test | K141: infra/prod | L141: Rollback < 10 phút | N141: =Settings!$C$5 -> 4 | P141: Chưa làm | Q141: =IF(OR(P141="Xong",P141="Bỏ"),"",IF(B141<TODAY(),"Quá hạn",IF(B141=TODAY(),"Hôm nay","")))
A142: 139 | B142: =WORKDAY(Settings!$C$4-1,A142,Holidays!$A$5:$A$40) -> 46519 | C142: S14 | D142: =INT((A142-1)/5)+1 -> 28 | E142: =MOD(A142-1,10)+1 -> 9 | F142: P3 · Hardening | G142: QC | H142: =IFERROR(INDEX(Roles!$D$5:$D$26,MATCH(G142,Roles!$A$5:$A$26,0)),"") -> medilens-qc-release-gatekeeper | I142: Chạy release_gate.py + viết readiness report | J142: Run release_gate.py + write readiness report | K142: qc/readiness-v1.md | L142: Khuyến nghị GO/NO-GO có số liệu | N142: =Settings!$C$5 -> 4 | P142: Chưa làm | Q142: =IF(OR(P142="Xong",P142="Bỏ"),"",IF(B142<TODAY(),"Quá hạn",IF(B142=TODAY(),"Hôm nay","")))
A143: 140 | B143: =WORKDAY(Settings!$C$4-1,A143,Holidays!$A$5:$A$40) -> 46520 | C143: S14 | D143: =INT((A143-1)/5)+1 -> 28 | E143: =MOD(A143-1,10)+1 -> 10 | F143: P3 · Hardening | G143: QC | H143: =IFERROR(INDEX(Roles!$D$5:$D$26,MATCH(G143,Roles!$A$5:$A$26,0)),"") -> medilens-qc-release-gatekeeper | I143: Cổng G3 + G3-P; Review + Retro | J143: Gates G3 + G3-P; review + retro | K143: gates/G3.md | L143: 0 High, 0 S1/S2, pentest sạch | M143: G3, G3-P | N143: =Settings!$C$5 -> 4 | P143: Chưa làm | Q143: =IF(OR(P143="Xong",P143="Bỏ"),"",IF(B143<TODAY(),"Quá hạn",IF(B143=TODAY(),"Hôm nay","")))
A144: 141 | B144: =WORKDAY(Settings!$C$4-1,A144,Holidays!$A$5:$A$40) -> 46521 | C144: S15 | D144: =INT((A144-1)/5)+1 -> 29 | E144: =MOD(A144-1,10)+1 -> 1 | F144: P4 · Beta & Launch v1.0 | G144: PM | H144: =IFERROR(INDEX(Roles!$D$5:$D$26,MATCH(G144,Roles!$A$5:$A$26,0)),"") -> medilens-product-manager | I144: Planning; kế hoạch beta, tiêu chí thành công, consent người tham gia | J144: Planning; beta plan, success criteria, participant consent | K144: beta/plan.md | L144: 10–20 người đã đồng ý | N144: =Settings!$C$5 -> 4 | P144: Chưa làm | Q144: =IF(OR(P144="Xong",P144="Bỏ"),"",IF(B144<TODAY(),"Quá hạn",IF(B144=TODAY(),"Hôm nay","")))
A145: 142 | B145: =WORKDAY(Settings!$C$4-1,A145,Holidays!$A$5:$A$40) -> 46524 | C145: S15 | D145: =INT((A145-1)/5)+1 -> 29 | E145: =MOD(A145-1,10)+1 -> 2 | F145: P4 · Beta & Launch v1.0 | G145: OPS | H145: =IFERROR(INDEX(Roles!$D$5:$D$26,MATCH(G145,Roles!$A$5:$A$26,0)),"") -> medilens-cloud-devops-engineer | I145: Feature flag, cấu hình prod, ngân sách + cảnh báo 80% | J145: Feature flags, prod config, budgets + 80% alerts | K145: config | L145: Cảnh báo ngân sách thử bắn | N145: =Settings!$C$5 -> 4 | P145: Chưa làm | Q145: =IF(OR(P145="Xong",P145="Bỏ"),"",IF(B145<TODAY(),"Quá hạn",IF(B145=TODAY(),"Hôm nay","")))
A146: 143 | B146: =WORKDAY(Settings!$C$4-1,A146,Holidays!$A$5:$A$40) -> 46525 | C146: S15 | D146: =INT((A146-1)/5)+1 -> 29 | E146: =MOD(A146-1,10)+1 -> 3 | F146: P4 · Beta & Launch v1.0 | G146: SUP | H146: =IFERROR(INDEX(Roles!$D$5:$D$26,MATCH(G146,Roles!$A$5:$A$26,0)),"") -> medilens-support-success | I146: Onboarding người beta, kênh phản hồi, mẫu phân loại phản hồi an toàn | J146: Onboard beta users, feedback channel, safety feedback triage template | K146: support/beta-onboarding | L146: Mọi người beta nhận hướng dẫn | N146: =Settings!$C$5 -> 4 | P146: Chưa làm | Q146: =IF(OR(P146="Xong",P146="Bỏ"),"",IF(B146<TODAY(),"Quá hạn",IF(B146=TODAY(),"Hôm nay","")))
A147: 144 | B147: =WORKDAY(Settings!$C$4-1,A147,Holidays!$A$5:$A$40) -> 46526 | C147: S15 | D147: =INT((A147-1)/5)+1 -> 29 | E147: =MOD(A147-1,10)+1 -> 4 | F147: P4 · Beta & Launch v1.0 | G147: SRE | H147: =IFERROR(INDEX(Roles!$D$5:$D$26,MATCH(G147,Roles!$A$5:$A$26,0)),"") -> medilens-sre-operations | I147: Lịch on-call cá nhân, kiểm cảnh báo end-to-end | J147: Personal on-call schedule; end-to-end alert test | K147: sre/oncall.md | L147: Cảnh báo tới điện thoại | N147: =Settings!$C$5 -> 4 | P147: Chưa làm | Q147: =IF(OR(P147="Xong",P147="Bỏ"),"",IF(B147<TODAY(),"Quá hạn",IF(B147=TODAY(),"Hôm nay","")))
A148: 145 | B148: =WORKDAY(Settings!$C$4-1,A148,Holidays!$A$5:$A$40) -> 46527 | C148: S15 | D148: =INT((A148-1)/5)+1 -> 29 | E148: =MOD(A148-1,10)+1 -> 5 | F148: P4 · Beta & Launch v1.0 | G148: BA | H148: =IFERROR(INDEX(Roles!$D$5:$D$26,MATCH(G148,Roles!$A$5:$A$26,0)),"") -> medilens-business-analyst | I148: Thu & phân loại phản hồi tuần 1 → backlog | J148: Collect and triage week-1 feedback → backlog | K148: beta/feedback-w1 | L148: Mỗi phản hồi có nhãn và ưu tiên | N148: =Settings!$C$5 -> 4 | P148: Chưa làm | Q148: =IF(OR(P148="Xong",P148="Bỏ"),"",IF(B148<TODAY(),"Quá hạn",IF(B148=TODAY(),"Hôm nay","")))
A149: 146 | B149: =WORKDAY(Settings!$C$4-1,A149,Holidays!$A$5:$A$40) -> 46528 | C149: S15 | D149: =INT((A149-1)/5)+1 -> 30 | E149: =MOD(A149-1,10)+1 -> 6 | F149: P4 · Beta & Launch v1.0 | G149: BE | H149: =IFERROR(INDEX(Roles!$D$5:$D$26,MATCH(G149,Roles!$A$5:$A$26,0)),"") -> medilens-backend-engineer | I149: Sửa lỗi beta ưu tiên (S1/S2 trước) | J149: Fix priority beta bugs (S1/S2 first) | K149: fix PRs | L149: Không còn S1 mở | N149: =Settings!$C$5 -> 4 | P149: Chưa làm | Q149: =IF(OR(P149="Xong",P149="Bỏ"),"",IF(B149<TODAY(),"Quá hạn",IF(B149=TODAY(),"Hôm nay","")))
A150: 147 | B150: =WORKDAY(Settings!$C$4-1,A150,Holidays!$A$5:$A$40) -> 46531 | C150: S15 | D150: =INT((A150-1)/5)+1 -> 30 | E150: =MOD(A150-1,10)+1 -> 7 | F150: P4 · Beta & Launch v1.0 | G150: AI | H150: =IFERROR(INDEX(Roles!$D$5:$D$26,MATCH(G150,Roles!$A$5:$A$26,0)),"") -> medilens-ai-ml-engineer | I150: Phân tích trường bị sửa nhiều nhất; prompt v3; eval lại | J150: Analyse most-corrected fields; prompt v3; re-evaluate | K150: ai/correction-analysis.md | L150: F1 không giảm so với G2 | N150: =Settings!$C$5 -> 4 | P150: Chưa làm | Q150: =IF(OR(P150="Xong",P150="Bỏ"),"",IF(B150<TODAY(),"Quá hạn",IF(B150=TODAY(),"Hôm nay","")))
A151: 148 | B151: =WORKDAY(Settings!$C$4-1,A151,Holidays!$A$5:$A$40) -> 46532 | C151: S15 | D151: =INT((A151-1)/5)+1 -> 30 | E151: =MOD(A151-1,10)+1 -> 8 | F151: P4 · Beta & Launch v1.0 | G151: CSO | H151: =IFERROR(INDEX(Roles!$D$5:$D$26,MATCH(G151,Roles!$A$5:$A$26,0)),"") -> medilens-clinical-safety-officer | I151: Rà soát báo cáo an toàn từ beta; cập nhật hazard log | J151: Review beta safety reports; update hazard log | K151: safety/hazard-log | L151: Mỗi báo cáo có kết luận | N151: =Settings!$C$5 -> 4 | P151: Chưa làm | Q151: =IF(OR(P151="Xong",P151="Bỏ"),"",IF(B151<TODAY(),"Quá hạn",IF(B151=TODAY(),"Hôm nay","")))
A152: 149 | B152: =WORKDAY(Settings!$C$4-1,A152,Holidays!$A$5:$A$40) -> 46533 | C152: S15 | D152: =INT((A152-1)/5)+1 -> 30 | E152: =MOD(A152-1,10)+1 -> 9 | F152: P4 · Beta & Launch v1.0 | G152: DE | H152: =IFERROR(INDEX(Roles!$D$5:$D$26,MATCH(G152,Roles!$A$5:$A$26,0)),"") -> medilens-data-engineer | I152: Dashboard sản phẩm: activation, North Star, retention | J152: Product dashboard: activation, North Star, retention | K152: dashboards/product | L152: Số liệu cập nhật hằng ngày | N152: =Settings!$C$5 -> 4 | P152: Chưa làm | Q152: =IF(OR(P152="Xong",P152="Bỏ"),"",IF(B152<TODAY(),"Quá hạn",IF(B152=TODAY(),"Hôm nay","")))
A153: 150 | B153: =WORKDAY(Settings!$C$4-1,A153,Holidays!$A$5:$A$40) -> 46534 | C153: S15 | D153: =INT((A153-1)/5)+1 -> 30 | E153: =MOD(A153-1,10)+1 -> 10 | F153: P4 · Beta & Launch v1.0 | G153: PM | H153: =IFERROR(INDEX(Roles!$D$5:$D$26,MATCH(G153,Roles!$A$5:$A$26,0)),"") -> medilens-product-manager | I153: Review beta + Retro; buffer | J153: Beta review + retro; buffer | K153: reports/sprint-15.md | L153: Quyết định tiếp tục/điều chỉnh | N153: =Settings!$C$5 -> 4 | P153: Chưa làm | Q153: =IF(OR(P153="Xong",P153="Bỏ"),"",IF(B153<TODAY(),"Quá hạn",IF(B153=TODAY(),"Hôm nay","")))
A154: 151 | B154: =WORKDAY(Settings!$C$4-1,A154,Holidays!$A$5:$A$40) -> 46535 | C154: S16 | D154: =INT((A154-1)/5)+1 -> 31 | E154: =MOD(A154-1,10)+1 -> 1 | F154: P4 · Beta & Launch v1.0 | G154: PM | H154: =IFERROR(INDEX(Roles!$D$5:$D$26,MATCH(G154,Roles!$A$5:$A$26,0)),"") -> medilens-product-manager | I154: Planning; launch checklist + kế hoạch truyền thông nhỏ | J154: Planning; launch checklist + small communication plan | K154: launch/checklist.md | L154: Checklist đủ mục | N154: =Settings!$C$5 -> 4 | P154: Chưa làm | Q154: =IF(OR(P154="Xong",P154="Bỏ"),"",IF(B154<TODAY(),"Quá hạn",IF(B154=TODAY(),"Hôm nay","")))
A155: 152 | B155: =WORKDAY(Settings!$C$4-1,A155,Holidays!$A$5:$A$40) -> 46538 | C155: S16 | D155: =INT((A155-1)/5)+1 -> 31 | E155: =MOD(A155-1,10)+1 -> 2 | F155: P4 · Beta & Launch v1.0 | G155: QA | H155: =IFERROR(INDEX(Roles!$D$5:$D$26,MATCH(G155,Roles!$A$5:$A$26,0)),"") -> medilens-qa-engineer | I155: Regression cuối + smoke test prod | J155: Final regression + prod smoke test | K155: qa/final-regression | L155: Xanh toàn bộ | N155: =Settings!$C$5 -> 4 | P155: Chưa làm | Q155: =IF(OR(P155="Xong",P155="Bỏ"),"",IF(B155<TODAY(),"Quá hạn",IF(B155=TODAY(),"Hôm nay","")))
... A162: 159 | B162: =WORKDAY(Settings!$C$4-1,A162,Holidays!$A$5:$A$40) -> 46547 | C162: S16 | D162: =INT((A162-1)/5)+1 -> 32 | E162: =MOD(A162-1,10)+1 -> 9 | F162: P4 · Beta & Launch v1.0 | G162: DE | H162: =IFERROR(INDEX(Roles!$D$5:$D$26,MATCH(G162,Roles!$A$5:$A$26,0)),"") -> medilens-data-engineer | I162: Báo cáo metric tuần đầu | J162: First-week metrics report | K162: reports/launch-week1.md | L162: Có so sánh với mục tiêu | N162: =Settings!$C$5 -> 4 | P162: Chưa làm | Q162: =IF(OR(P162="Xong",P162="Bỏ"),"",IF(B162<TODAY(),"Quá hạn",IF(B162=TODAY(),"Hôm nay","")))
A163: 160 | B163: =WORKDAY(Settings!$C$4-1,A163,Holidays!$A$5:$A$40) -> 46548 | C163: S16 | D163: =INT((A163-1)/5)+1 -> 32 | E163: =MOD(A163-1,10)+1 -> 10 | F163: P4 · Beta & Launch v1.0 | G163: QC | H163: =IFERROR(INDEX(Roles!$D$5:$D$26,MATCH(G163,Roles!$A$5:$A$26,0)),"") -> medilens-qc-release-gatekeeper | I163: Cổng G4 launch review + post-launch retro | J163: Gate G4 launch review + post-launch retro | K163: gates/G4.md | L163: Metric beta đạt; retro có hành động | M163: G4 | N163: =Settings!$C$5 -> 4 | P163: Chưa làm | Q163: =IF(OR(P163="Xong",P163="Bỏ"),"",IF(B163<TODAY(),"Quá hạn",IF(B163=TODAY(),"Hôm nay","")))
A164: 161 | B164: =WORKDAY(Settings!$C$4-1,A164,Holidays!$A$5:$A$40) -> 46549 | C164: S17 | D164: =INT((A164-1)/5)+1 -> 33 | E164: =MOD(A164-1,10)+1 -> 1 | F164: P5 · Hypercare & v1.5 | G164: PM | H164: =IFERROR(INDEX(Roles!$D$5:$D$26,MATCH(G164,Roles!$A$5:$A$26,0)),"") -> medilens-product-manager | I164: Planning; backlog v1.5 ưu tiên bằng RICE (rice_score.py) | J164: Planning; v1.5 backlog prioritised with RICE (rice_score.py) | K164: product/v1.5-backlog | L164: Top 10 có điểm RICE | N164: =Settings!$C$5 -> 4 | P164: Chưa làm | Q164: =IF(OR(P164="Xong",P164="Bỏ"),"",IF(B164<TODAY(),"Quá hạn",IF(B164=TODAY(),"Hôm nay","")))
A165: 162 | B165: =WORKDAY(Settings!$C$4-1,A165,Holidays!$A$5:$A$40) -> 46552 | C165: S17 | D165: =INT((A165-1)/5)+1 -> 33 | E165: =MOD(A165-1,10)+1 -> 2 | F165: P5 · Hypercare & v1.5 | G165: BE | H165: =IFERROR(INDEX(Roles!$D$5:$D$26,MATCH(G165,Roles!$A$5:$A$26,0)),"") -> medilens-backend-engineer | I165: Nhập PDF có lớp chữ: trích trực tiếp, bỏ OCR (BR-045) | J165: Text-layer PDF import: extract directly, skip OCR (BR-045) | K165: import/pdf | L165: Test BR-045 qua | N165: =Settings!$C$5 -> 4 | P165: Chưa làm | Q165: =IF(OR(P165="Xong",P165="Bỏ"),"",IF(B165<TODAY(),"Quá hạn",IF(B165=TODAY(),"Hôm nay","")))
A166: 163 | B166: =WORKDAY(Settings!$C$4-1,A166,Holidays!$A$5:$A$40) -> 46553 | C166: S17 | D166: =INT((A166-1)/5)+1 -> 33 | E166: =MOD(A166-1,10)+1 -> 3 | F166: P5 · Hypercare & v1.5 | G166: BE | H166: =IFERROR(INDEX(Roles!$D$5:$D$26,MATCH(G166,Roles!$A$5:$A$26,0)),"") -> medilens-backend-engineer | I166: Nhập DOCX; chặn macro và đối tượng nhúng | J166: DOCX import; block macros and embedded objects | K166: import/docx | L166: File có macro bị từ chối | N166: =Settings!$C$5 -> 4 | P166: Chưa làm | Q166: =IF(OR(P166="Xong",P166="Bỏ"),"",IF(B166<TODAY(),"Quá hạn",IF(B166=TODAY(),"Hôm nay","")))
A167: 164 | B167: =WORKDAY(Settings!$C$4-1,A167,Holidays!$A$5:$A$40) -> 46554 | C167: S17 | D167: =INT((A167-1)/5)+1 -> 33 | E167: =MOD(A167-1,10)+1 -> 4 | F167: P5 · Hypercare & v1.5 | G167: CIN | H167: =IFERROR(INDEX(Roles!$D$5:$D$26,MATCH(G167,Roles!$A$5:$A$26,0)),"") -> medilens-clinical-informaticist | I167: Nhập FHIR R4 Bundle: map Condition/Observation/Procedure không qua LLM | J167: FHIR R4 Bundle import: map Condition/Observation/Procedure without LLM | K167: import/fhir | L167: Bundle mẫu map đúng 100% | N167: =Settings!$C$5 -> 4 | P167: Chưa làm | Q167: =IF(OR(P167="Xong",P167="Bỏ"),"",IF(B167<TODAY(),"Quá hạn",IF(B167=TODAY(),"Hôm nay","")))
A168: 165 | B168: =WORKDAY(Settings!$C$4-1,A168,Holidays!$A$5:$A$40) -> 46555 | C168: S17 | D168: =INT((A168-1)/5)+1 -> 33 | E168: =MOD(A168-1,10)+1 -> 5 | F168: P5 · Hypercare & v1.5 | G168: QA | H168: =IFERROR(INDEX(Roles!$D$5:$D$26,MATCH(G168,Roles!$A$5:$A$26,0)),"") -> medilens-qa-engineer | I168: Test import + file độc (PDF chứa JS, DOCX macro, FHIR sai schema) | J168: Import tests + malicious files (JS-PDF, macro DOCX, invalid FHIR) | K168: tests/import | L168: Xanh trong CI | N168: =Settings!$C$5 -> 4 | P168: Chưa làm | Q168: =IF(OR(P168="Xong",P168="Bỏ"),"",IF(B168<TODAY(),"Quá hạn",IF(B168=TODAY(),"Hôm nay","")))
A169: 166 | B169: =WORKDAY(Settings!$C$4-1,A169,Holidays!$A$5:$A$40) -> 46556 | C169: S17 | D169: =INT((A169-1)/5)+1 -> 34 | E169: =MOD(A169-1,10)+1 -> 6 | F169: P5 · Hypercare & v1.5 | G169: AI | H169: =IFERROR(INDEX(Roles!$D$5:$D$26,MATCH(G169,Roles!$A$5:$A$26,0)),"") -> medilens-ai-ml-engineer | I169: Hợp nhất nguồn mâu thuẫn: record > image_derived > patient_reported + cảnh báo (BR-044) | J169: Merge conflicting sources: record > image_derived > patient_reported + warning (BR-044) | K169: merge logic | L169: Test BR-044 qua | N169: =Settings!$C$5 -> 4 | P169: Chưa làm | Q169: =IF(OR(P169="Xong",P169="Bỏ"),"",IF(B169<TODAY(),"Quá hạn",IF(B169=TODAY(),"Hôm nay","")))
A170: 167 | B170: =WORKDAY(Settings!$C$4-1,A170,Holidays!$A$5:$A$40) -> 46559 | C170: S17 | D170: =INT((A170-1)/5)+1 -> 34 | E170: =MOD(A170-1,10)+1 -> 7 | F170: P5 · Hypercare & v1.5 | G170: MLO | H170: =IFERROR(INDEX(Roles!$D$5:$D$26,MATCH(G170,Roles!$A$5:$A$26,0)),"") -> medilens-mlops-engineer | I170: Dashboard chi phí: USD/tài liệu, cache hit, tỉ lệ chuyển tầng | J170: Cost dashboard: USD/doc, cache hit, escalation rate | K170: dashboards/cost | L170: Cảnh báo vượt ngân sách ngày | N170: =Settings!$C$5 -> 4 | P170: Chưa làm | Q170: =IF(OR(P170="Xong",P170="Bỏ"),"",IF(B170<TODAY(),"Quá hạn",IF(B170=TODAY(),"Hôm nay","")))
A171: 168 | B171: =WORKDAY(Settings!$C$4-1,A171,Holidays!$A$5:$A$40) -> 46560 | C171: S17 | D171: =INT((A171-1)/5)+1 -> 34 | E171: =MOD(A171-1,10)+1 -> 8 | F171: P5 · Hypercare & v1.5 | G171: SUP | H171: =IFERROR(INDEX(Roles!$D$5:$D$26,MATCH(G171,Roles!$A$5:$A$26,0)),"") -> medilens-support-success | I171: Hypercare: cập nhật knowledge base từ ticket | J171: Hypercare: update knowledge base from tickets | K171: support/kb | L171: Top-10 câu hỏi có bài KB | N171: =Settings!$C$5 -> 4 | P171: Chưa làm | Q171: =IF(OR(P171="Xong",P171="Bỏ"),"",IF(B171<TODAY(),"Quá hạn",IF(B171=TODAY(),"Hôm nay","")))
A172: 169 | B172: =WORKDAY(Settings!$C$4-1,A172,Holidays!$A$5:$A$40) -> 46561 | C172: S17 | D172: =INT((A172-1)/5)+1 -> 34 | E172: =MOD(A172-1,10)+1 -> 9 | F172: P5 · Hypercare & v1.5 | G172: SRE | H172: =IFERROR(INDEX(Roles!$D$5:$D$26,MATCH(G172,Roles!$A$5:$A$26,0)),"") -> medilens-sre-operations | I172: Error budget review (error_budget.py) | J172: Error budget review (error_budget.py) | K172: sre/error-budget.md | L172: Quyết định theo chính sách error budget | N172: =Settings!$C$5 -> 4 | P172: Chưa làm | Q172: =IF(OR(P172="Xong",P172="Bỏ"),"",IF(B172<TODAY(),"Quá hạn",IF(B172=TODAY(),"Hôm nay","")))
A173: 170 | B173: =WORKDAY(Settings!$C$4-1,A173,Holidays!$A$5:$A$40) -> 46562 | C173: S17 | D173: =INT((A173-1)/5)+1 -> 34 | E173: =MOD(A173-1,10)+1 -> 10 | F173: P5 · Hypercare & v1.5 | G173: PM | H173: =IFERROR(INDEX(Roles!$D$5:$D$26,MATCH(G173,Roles!$A$5:$A$26,0)),"") -> medilens-product-manager | I173: Review + Retro; buffer | J173: Review + retro; buffer | K173: reports/sprint-17.md | L173: Demo được ghi hình | N173: =Settings!$C$5 -> 4 | P173: Chưa làm | Q173: =IF(OR(P173="Xong",P173="Bỏ"),"",IF(B173<TODAY(),"Quá hạn",IF(B173=TODAY(),"Hôm nay","")))
A174: 171 | B174: =WORKDAY(Settings!$C$4-1,A174,Holidays!$A$5:$A$40) -> 46563 | C174: S18 | D174: =INT((A174-1)/5)+1 -> 35 | E174: =MOD(A174-1,10)+1 -> 1 | F174: P5 · Hypercare & v1.5 | G174: UX | H174: =IFERROR(INDEX(Roles!$D$5:$D$26,MATCH(G174,Roles!$A$5:$A$26,0)),"") -> medilens-ux-ui-designer | I174: Planning; spec template theo giới/tuổi, organ_status, biểu tượng dụng cụ | J174: Planning; spec for sex/age templates, organ_status, device glyphs | K174: Figma spec | L174: Mọi loại lệch ở 27.1 có cách hiển thị | N174: =Settings!$C$5 -> 4 | P174: Chưa làm | Q174: =IF(OR(P174="Xong",P174="Bỏ"),"",IF(B174<TODAY(),"Quá hạn",IF(B174=TODAY(),"Hôm nay","")))
A175: 172 | B175: =WORKDAY(Settings!$C$4-1,A175,Holidays!$A$5:$A$40) -> 46566 | C175: S18 | D175: =INT((A175-1)/5)+1 -> 35 | E175: =MOD(A175-1,10)+1 -> 2 | F175: P5 · Hypercare & v1.5 | G175: ART | H175: =IFERROR(INDEX(Roles!$D$5:$D$26,MATCH(G175,Roles!$A$5:$A$26,0)),"") -> medilens-3d-medical-artist | I175: Template nam/nữ/trẻ em; mesh có thể ẩn; glyph implant/stent/máy tạo nhịp | J175: Male/female/child templates; hideable meshes; implant/stent/pacemaker glyphs | K175: assets/templates | L175: check_glb_regions.py qua cho mọi template | N175: =Settings!$C$5 -> 4 | P175: Chưa làm | Q175: =IF(OR(P175="Xong",P175="Bỏ"),"",IF(B175<TODAY(),"Quá hạn",IF(B175=TODAY(),"Hôm nay","")))
... A182: 179 | B182: =WORKDAY(Settings!$C$4-1,A182,Holidays!$A$5:$A$40) -> 46575 | C182: S18 | D182: =INT((A182-1)/5)+1 -> 36 | E182: =MOD(A182-1,10)+1 -> 9 | F182: P5 · Hypercare & v1.5 | G182: SUP | H182: =IFERROR(INDEX(Roles!$D$5:$D$26,MATCH(G182,Roles!$A$5:$A$26,0)),"") -> medilens-support-success | I182: Đánh giá hypercare: S1/S2, SLO, backlog hỗ trợ | J182: Hypercare assessment: S1/S2, SLOs, support backlog | K182: support/hypercare-report.md | L182: Đủ dữ liệu cho G5-H | N182: =Settings!$C$5 -> 4 | P182: Chưa làm | Q182: =IF(OR(P182="Xong",P182="Bỏ"),"",IF(B182<TODAY(),"Quá hạn",IF(B182=TODAY(),"Hôm nay","")))
A183: 180 | B183: =WORKDAY(Settings!$C$4-1,A183,Holidays!$A$5:$A$40) -> 46576 | C183: S18 | D183: =INT((A183-1)/5)+1 -> 36 | E183: =MOD(A183-1,10)+1 -> 10 | F183: P5 · Hypercare & v1.5 | G183: QC | H183: =IFERROR(INDEX(Roles!$D$5:$D$26,MATCH(G183,Roles!$A$5:$A$26,0)),"") -> medilens-qc-release-gatekeeper | I183: Cổng G5-H; Review + Retro | J183: Gate G5-H; review + retro | K183: gates/G5-H.md | L183: Tiêu chí G5-H đạt | M183: G5-H | N183: =Settings!$C$5 -> 4 | P183: Chưa làm | Q183: =IF(OR(P183="Xong",P183="Bỏ"),"",IF(B183<TODAY(),"Quá hạn",IF(B183=TODAY(),"Hôm nay","")))
A184: 181 | B184: =WORKDAY(Settings!$C$4-1,A184,Holidays!$A$5:$A$40) -> 46577 | C184: S19 | D184: =INT((A184-1)/5)+1 -> 37 | E184: =MOD(A184-1,10)+1 -> 1 | F184: P5 · Hypercare & v1.5 | G184: BA | H184: =IFERROR(INDEX(Roles!$D$5:$D$26,MATCH(G184,Roles!$A$5:$A$26,0)),"") -> medilens-business-analyst | I184: Planning; BR + extraction schema cho 2 Unit mới | J184: Planning; BRs + extraction schema for 2 new Units | K184: units spec | L184: Schema được AI và CIN review | N184: =Settings!$C$5 -> 4 | P184: Chưa làm | Q184: =IF(OR(P184="Xong",P184="Bỏ"),"",IF(B184<TODAY(),"Quá hạn",IF(B184=TODAY(),"Hôm nay","")))
A185: 182 | B185: =WORKDAY(Settings!$C$4-1,A185,Holidays!$A$5:$A$40) -> 46580 | C185: S19 | D185: =INT((A185-1)/5)+1 -> 37 | E185: =MOD(A185-1,10)+1 -> 2 | F185: P5 · Hypercare & v1.5 | G185: ART | H185: =IFERROR(INDEX(Roles!$D$5:$D$26,MATCH(G185,Roles!$A$5:$A$26,0)),"") -> medilens-3d-medical-artist | I185: Mesh phổi (theo thùy), thận/niệu quản/bàng quang theo region_code | J185: Lung (by lobe), kidney/ureter/bladder meshes by region_code | K185: assets/resp, assets/uro | L185: check_glb_regions.py qua | N185: =Settings!$C$5 -> 4 | P185: Chưa làm | Q185: =IF(OR(P185="Xong",P185="Bỏ"),"",IF(B185<TODAY(),"Quá hạn",IF(B185=TODAY(),"Hôm nay","")))
...

Sheet Gates
A1: 14 cổng chất lượng / Quality gates
A2: G0–G4: cổng gốc (mục 5). G0-R, G1-D, G2-CS, G3-P, G5-H: cổng bổ sung (mục 22.4). G5, G6: phát hành v1.5, v2.0.
A3: Cổng | B3: Tên (VI) | C3: Name (EN) | D3: Sprint | E3: Ngày dự kiến | F3: Tiêu chí (VI) | G3: Criteria (EN) | H3: Bằng chứng | I3: Người duyệt (role) | J3: Trạng thái | K3: Ngày quyết định | L3: Ghi chú
A4: G0 | B4: Discovery Go/No-Go | C4: Discovery Go/No-Go | D4: S02 | E4: =INDEX(Sprints!$E$4:$E$29,MATCH(D4,Sprints!$A$4:$A$29,0)) -> 46339 | F4: Product Brief, BRD v1, prototype được duyệt; phạm vi MVP 3 Unit khóa bằng MoSCoW | G4: Product brief, BRD v1 and prototype approved; MVP scope locked to 3 Units (MoSCoW) | H4: gates/G0.md, BRD-v1, prototype link | I4: PM + QC | J4: Chưa đến
A5: G0-R | B5: Regulatory | C5: Regulatory | D5: S02 | E5: =INDEX(Sprints!$E$4:$E$29,MATCH(D5,Sprints!$A$4:$A$29,0)) -> 46339 | F5: Intended Use Statement + Regulatory Decision Record được duyệt; danh sách từ cấm trong claims | G5: Intended Use Statement + Regulatory Decision Record approved; forbidden-claims list | H5: regulatory/intended-use.md, RDR-001 | I5: REG | J5: Chưa đến
A6: G1 | B6: Kiến trúc sẵn sàng | C6: Architecture ready | D6: S05 | E6: =INDEX(Sprints!$E$4:$E$29,MATCH(D6,Sprints!$A$4:$A$29,0)) -> 46384 | F6: ADR chốt, CI xanh, 1 tài liệu chạy trọn pipeline trên staging, threat model v1 | G6: ADRs final, CI green, one document end-to-end on staging, threat model v1 | H6: gates/G1.md, CI run, staging trace | I6: SA + QC | J6: Chưa đến
A7: G1-D | B7: Data licence (lần 1: dữ liệu đánh giá) | C7: Data licence (round 1: evaluation data) | D7: S05 | E7: =INDEX(Sprints!$E$4:$E$29,MATCH(D7,Sprints!$A$4:$A$29,0)) -> 46384 | F7: Checklist 25.6 đạt cho golden set và dữ liệu synthetic: license, Dataset Card, checksum, không rò rỉ | G7: Checklist 25.6 passed for golden set and synthetic data: licence, Dataset Card, checksum, no leakage | H7: license-register.csv, dataset cards | I7: DC + REG | J7: Chưa đến
A8: G2 | B8: Feature complete | C8: Feature complete | D8: S11 | E8: =INDEX(Sprints!$E$4:$E$29,MATCH(D8,Sprints!$A$4:$A$29,0)) -> 46476 | F8: Mọi mục Must xong; F1 trích xuất ≥ 0,80 trên golden set 600 mẫu; region accuracy ≥ 0,85 | G8: All Must items done; extraction F1 ≥ 0.80 on 600-doc golden set; region accuracy ≥ 0.85 | H8: evaluation report, backlog | I8: QC | J8: Chưa đến
A9: G2-CS | B9: Clinical safety | C9: Clinical safety | D9: S13 | E9: =INDEX(Sprints!$E$4:$E$29,MATCH(D9,Sprints!$A$4:$A$29,0)) -> 46505 | F9: Hazard log không còn rủi ro không chấp nhận được; Clinical Safety Case được ký | G9: No unacceptable risk left in hazard log; Clinical Safety Case signed | H9: safety/CSC.md, hazard-log | I9: CSO | J9: Chưa đến
A10: G3 | B10: Release gate | C10: Release gate | D10: S14 | E10: =INDEX(Sprints!$E$4:$E$29,MATCH(D10,Sprints!$A$4:$A$29,0)) -> 46520 | F10: 0 lỗ hổng High, 0 bug S1/S2, SLO đạt trên staging, Security Evidence Pack đầy đủ | G10: 0 High vulnerabilities, 0 S1/S2 bugs, SLOs met on staging, complete Security Evidence Pack | H10: release_gate.py output, readiness report | I10: QC | J10: Chưa đến
A11: G3-P | B11: External pentest | C11: External pentest | D11: S14 | E11: =INDEX(Sprints!$E$4:$E$29,MATCH(D11,Sprints!$A$4:$A$29,0)) -> 46520 | F11: Pentest độc lập: không còn High/Critical; báo cáo lưu hồ sơ; điều kiện để nhận dữ liệu thật | G11: Independent pentest: no High/Critical open; report archived; prerequisite for real data | H11: pentest report, retest | I11: SEC | J11: Chưa đến
A12: G4 | B12: Launch review | C12: Launch review | D12: S16 | E12: =INDEX(Sprints!$E$4:$E$29,MATCH(D12,Sprints!$A$4:$A$29,0)) -> 46548 | F12: Metric beta đạt; Go/No-Go ghi biên bản; post-launch retro | G12: Beta metrics met; Go/No-Go minuted; post-launch retro | H12: gates/G4.md, beta report | I12: PM + QC | J12: Chưa đến
A13: G5-H | B13: Hypercare exit | C13: Hypercare exit | D13: S18 | E13: =INDEX(Sprints!$E$4:$E$29,MATCH(D13,Sprints!$A$4:$A$29,0)) -> 46576 | F13: Không có S1/S2 mới trong 2 tuần, SLO đạt, backlog hỗ trợ ổn định | G13: No new S1/S2 for 2 weeks, SLOs met, support backlog stable | H13: hypercare report | I13: SUP + SRE | J13: Chưa đến
A14: G5 | B14: Release v1.5 | C14: Release v1.5 | D14: S20 | E14: =INDEX(Sprints!$E$4:$E$29,MATCH(D14,Sprints!$A$4:$A$29,0)) -> 46604 | F14: Release gate cho bản v1.5: import số, 2 Unit mới, template, cascade; bảo mật đã rà soát | G14: Release gate for v1.5: digital import, 2 new Units, templates, cascade; security reviewed | H14: readiness report v1.5 | I14: QC | J14: Chưa đến
A15: G0-R (CT) | B15: Regulatory — tái đánh giá cho CT | C15: Regulatory — re-assessment for CT | D15: S21 | E15: =INDEX(Sprints!$E$4:$E$29,MATCH(D15,Sprints!$A$4:$A$29,0)) -> 46618 | F15: RDR cập nhật cho CT; xác nhận BR-042 (chỉ dựng giải phẫu minh họa); ý kiến chuyên gia nếu cần | G15: RDR updated for CT; BR-042 confirmed (illustrative anatomy only); expert advice if needed | H15: RDR-002 | I15: REG + CSO | J15: Chưa đến
... A17: G6 | B17: Release v2.0 | C17: Release v2.0 | D17: S26 | E17: =INDEX(Sprints!$E$4:$E$29,MATCH(D17,Sprints!$A$4:$A$29,0)) -> 46692 | F17: Release gate v2: xác thực lâm sàng CT, pentest delta sạch, registration error < 15 mm, chi phí trong ngân sách | G17: v2 release gate: CT clinical validation, clean delta pentest, registration error < 15 mm, cost within budget | H17: readiness report v2, closure report | I17: QC + steering | J17: Chưa đến

Sheet Roles
A1: Role và skill / Roles and skills
A2: 22 role (13 role gốc + 9 role bổ sung ở mục 23). Cột Skill là tên skill agent cần gọi. ★ = cần người thật trước dữ liệu thật/ra mắt.
A4: Mã | B4: Role (VI) | C4: Role (EN) | D4: Skill | E4: Cần người thật? | F4: Số ngày | G4: Giờ KH | H4: Giờ TT | I4: Tỷ trọng giờ
A5: PM | B5: Product/Project Manager (PO, Scrum Master, Delivery) | C5: Product/Project Manager (PO, Scrum Master, Delivery) | D5: medilens-product-manager | F5: =COUNTIF('Daily Plan'!$G$4:$G$263,A5) -> 25 | G5: =SUMIFS('Daily Plan'!$N$4:$N$263,'Daily Plan'!$G$4:$G$263,A5) -> 100 | H5: =SUMIFS('Daily Plan'!$O$4:$O$263,'Daily Plan'!$G$4:$G$263,A5) -> 0 | I5: =IF(SUM($G$5:$G$26)=0,0,G5/SUM($G$5:$G$26)) -> 0.096153846
A6: BA | B6: Business Analyst | C6: Business Analyst | D6: medilens-business-analyst | F6: =COUNTIF('Daily Plan'!$G$4:$G$263,A6) -> 8 | G6: =SUMIFS('Daily Plan'!$N$4:$N$263,'Daily Plan'!$G$4:$G$263,A6) -> 32 | H6: =SUMIFS('Daily Plan'!$O$4:$O$263,'Daily Plan'!$G$4:$G$263,A6) -> 0 | I6: =IF(SUM($G$5:$G$26)=0,0,G6/SUM($G$5:$G$26)) -> 0.030769231
A7: UX | B7: UX/UI Designer | C7: UX/UI Designer | D7: medilens-ux-ui-designer | F7: =COUNTIF('Daily Plan'!$G$4:$G$263,A7) -> 10 | G7: =SUMIFS('Daily Plan'!$N$4:$N$263,'Daily Plan'!$G$4:$G$263,A7) -> 40 | H7: =SUMIFS('Daily Plan'!$O$4:$O$263,'Daily Plan'!$G$4:$G$263,A7) -> 0 | I7: =IF(SUM($G$5:$G$26)=0,0,G7/SUM($G$5:$G$26)) -> 0.038461538
A8: SA | B8: Solution Architect | C8: Solution Architect | D8: medilens-solution-architect | F8: =COUNTIF('Daily Plan'!$G$4:$G$263,A8) -> 3 | G8: =SUMIFS('Daily Plan'!$N$4:$N$263,'Daily Plan'!$G$4:$G$263,A8) -> 12 | H8: =SUMIFS('Daily Plan'!$O$4:$O$263,'Daily Plan'!$G$4:$G$263,A8) -> 0 | I8: =IF(SUM($G$5:$G$26)=0,0,G8/SUM($G$5:$G$26)) -> 0.011538462
A9: AI | B9: AI/ML Engineer (OCR, CV, LLM) | C9: AI/ML Engineer (OCR, CV, LLM) | D9: medilens-ai-ml-engineer | F9: =COUNTIF('Daily Plan'!$G$4:$G$263,A9) -> 27 | G9: =SUMIFS('Daily Plan'!$N$4:$N$263,'Daily Plan'!$G$4:$G$263,A9) -> 108 | H9: =SUMIFS('Daily Plan'!$O$4:$O$263,'Daily Plan'!$G$4:$G$263,A9) -> 0 | I9: =IF(SUM($G$5:$G$26)=0,0,G9/SUM($G$5:$G$26)) -> 0.10384615
A10: DE | B10: Data Engineer | C10: Data Engineer | D10: medilens-data-engineer | F10: =COUNTIF('Daily Plan'!$G$4:$G$263,A10) -> 5 | G10: =SUMIFS('Daily Plan'!$N$4:$N$263,'Daily Plan'!$G$4:$G$263,A10) -> 20 | H10: =SUMIFS('Daily Plan'!$O$4:$O$263,'Daily Plan'!$G$4:$G$263,A10) -> 0 | I10: =IF(SUM($G$5:$G$26)=0,0,G10/SUM($G$5:$G$26)) -> 0.019230769
A11: BE | B11: Backend Engineer | C11: Backend Engineer | D11: medilens-backend-engineer | F11: =COUNTIF('Daily Plan'!$G$4:$G$263,A11) -> 25 | G11: =SUMIFS('Daily Plan'!$N$4:$N$263,'Daily Plan'!$G$4:$G$263,A11) -> 100 | H11: =SUMIFS('Daily Plan'!$O$4:$O$263,'Daily Plan'!$G$4:$G$263,A11) -> 0 | I11: =IF(SUM($G$5:$G$26)=0,0,G11/SUM($G$5:$G$26)) -> 0.096153846
A12: FE | B12: Frontend Engineer (viewer 3D/2D) | C12: Frontend Engineer (3D/2D viewer) | D12: medilens-frontend-engineer | F12: =COUNTIF('Daily Plan'!$G$4:$G$263,A12) -> 20 | G12: =SUMIFS('Daily Plan'!$N$4:$N$263,'Daily Plan'!$G$4:$G$263,A12) -> 80 | H12: =SUMIFS('Daily Plan'!$O$4:$O$263,'Daily Plan'!$G$4:$G$263,A12) -> 0 | I12: =IF(SUM($G$5:$G$26)=0,0,G12/SUM($G$5:$G$26)) -> 0.076923077
A13: OPS | B13: Cloud/DevOps Engineer (+ FinOps hạ tầng) | C13: Cloud/DevOps Engineer (+ infra FinOps) | D13: medilens-cloud-devops-engineer | F13: =COUNTIF('Daily Plan'!$G$4:$G$263,A13) -> 13 | G13: =SUMIFS('Daily Plan'!$N$4:$N$263,'Daily Plan'!$G$4:$G$263,A13) -> 52 | H13: =SUMIFS('Daily Plan'!$O$4:$O$263,'Daily Plan'!$G$4:$G$263,A13) -> 0 | I13: =IF(SUM($G$5:$G$26)=0,0,G13/SUM($G$5:$G$26)) -> 0.05
A14: SEC | B14: Security Engineer | C14: Security Engineer | D14: medilens-security-engineer | E14: Pentest độc lập trước G3-P | F14: =COUNTIF('Daily Plan'!$G$4:$G$263,A14) -> 13 | G14: =SUMIFS('Daily Plan'!$N$4:$N$263,'Daily Plan'!$G$4:$G$263,A14) -> 52 | H14: =SUMIFS('Daily Plan'!$O$4:$O$263,'Daily Plan'!$G$4:$G$263,A14) -> 0 | I14: =IF(SUM($G$5:$G$26)=0,0,G14/SUM($G$5:$G$26)) -> 0.05
A15: QA | B15: QA Engineer | C15: QA Engineer | D15: medilens-qa-engineer | F15: =COUNTIF('Daily Plan'!$G$4:$G$263,A15) -> 19 | G15: =SUMIFS('Daily Plan'!$N$4:$N$263,'Daily Plan'!$G$4:$G$263,A15) -> 76 | H15: =SUMIFS('Daily Plan'!$O$4:$O$263,'Daily Plan'!$G$4:$G$263,A15) -> 0 | I15: =IF(SUM($G$5:$G$26)=0,0,G15/SUM($G$5:$G$26)) -> 0.073076923
A16: QC | B16: QC / Release Gatekeeper | C16: QC / Release Gatekeeper | D16: medilens-qc-release-gatekeeper | F16: =COUNTIF('Daily Plan'!$G$4:$G$263,A16) -> 13 | G16: =SUMIFS('Daily Plan'!$N$4:$N$263,'Daily Plan'!$G$4:$G$263,A16) -> 52 | H16: =SUMIFS('Daily Plan'!$O$4:$O$263,'Daily Plan'!$G$4:$G$263,A16) -> 0 | I16: =IF(SUM($G$5:$G$26)=0,0,G16/SUM($G$5:$G$26)) -> 0.05
A17: SRE | B17: SRE / Vận hành & bảo trì | C17: SRE / Operations & maintenance | D17: medilens-sre-operations | F17: =COUNTIF('Daily Plan'!$G$4:$G$263,A17) -> 8 | G17: =SUMIFS('Daily Plan'!$N$4:$N$263,'Daily Plan'!$G$4:$G$263,A17) -> 32 | H17: =SUMIFS('Daily Plan'!$O$4:$O$263,'Daily Plan'!$G$4:$G$263,A17) -> 0 | I17: =IF(SUM($G$5:$G$26)=0,0,G17/SUM($G$5:$G$26)) -> 0.030769231
A18: CSO | B18: ★ Clinical Safety Officer (bác sĩ cố vấn) | C18: ★ Clinical Safety Officer (clinical advisor) | D18: medilens-clinical-safety-officer | E18: Có — bác sĩ cố vấn ký G2-CS | F18: =COUNTIF('Daily Plan'!$G$4:$G$263,A18) -> 12 | G18: =SUMIFS('Daily Plan'!$N$4:$N$263,'Daily Plan'!$G$4:$G$263,A18) -> 48 | H18: =SUMIFS('Daily Plan'!$O$4:$O$263,'Daily Plan'!$G$4:$G$263,A18) -> 0 | I18: =IF(SUM($G$5:$G$26)=0,0,G18/SUM($G$5:$G$26)) -> 0.046153846
A19: REG | B19: ★ Regulatory, Privacy & Legal (DPO) | C19: ★ Regulatory, Privacy & Legal (DPO) | D19: medilens-regulatory-privacy-officer | E19: Có — tư vấn luật trước dữ liệu thật | F19: =COUNTIF('Daily Plan'!$G$4:$G$263,A19) -> 11 | G19: =SUMIFS('Daily Plan'!$N$4:$N$263,'Daily Plan'!$G$4:$G$263,A19) -> 44 | H19: =SUMIFS('Daily Plan'!$O$4:$O$263,'Daily Plan'!$G$4:$G$263,A19) -> 0 | I19: =IF(SUM($G$5:$G$26)=0,0,G19/SUM($G$5:$G$26)) -> 0.042307692
A20: CIN | B20: Clinical Informaticist (FHIR, ICD-10, LOINC, DICOM) | C20: Clinical Informaticist (FHIR, ICD-10, LOINC, DICOM) | D20: medilens-clinical-informaticist | F20: =COUNTIF('Daily Plan'!$G$4:$G$263,A20) -> 5 | G20: =SUMIFS('Daily Plan'!$N$4:$N$263,'Daily Plan'!$G$4:$G$263,A20) -> 20 | H20: =SUMIFS('Daily Plan'!$O$4:$O$263,'Daily Plan'!$G$4:$G$263,A20) -> 0 | I20: =IF(SUM($G$5:$G$26)=0,0,G20/SUM($G$5:$G$26)) -> 0.019230769
A21: DC | B21: ★ Data Curator & Annotation Lead | C21: ★ Data Curator & Annotation Lead | D21: medilens-data-curator | E21: Có — người gán nhãn có chuyên môn | F21: =COUNTIF('Daily Plan'!$G$4:$G$263,A21) -> 7 | G21: =SUMIFS('Daily Plan'!$N$4:$N$263,'Daily Plan'!$G$4:$G$263,A21) -> 28 | H21: =SUMIFS('Daily Plan'!$O$4:$O$263,'Daily Plan'!$G$4:$G$263,A21) -> 0 | I21: =IF(SUM($G$5:$G$26)=0,0,G21/SUM($G$5:$G$26)) -> 0.026923077
A22: MLO | B22: MLOps Engineer (+ FinOps token) | C22: MLOps Engineer (+ token FinOps) | D22: medilens-mlops-engineer | F22: =COUNTIF('Daily Plan'!$G$4:$G$263,A22) -> 10 | G22: =SUMIFS('Daily Plan'!$N$4:$N$263,'Daily Plan'!$G$4:$G$263,A22) -> 40 | H22: =SUMIFS('Daily Plan'!$O$4:$O$263,'Daily Plan'!$G$4:$G$263,A22) -> 0 | I22: =IF(SUM($G$5:$G$26)=0,0,G22/SUM($G$5:$G$26)) -> 0.038461538
A23: IMG | B23: Medical Imaging Engineer (CT/DICOM) | C23: Medical Imaging Engineer (CT/DICOM) | D23: medilens-medical-imaging-engineer | F23: =COUNTIF('Daily Plan'!$G$4:$G$263,A23) -> 8 | G23: =SUMIFS('Daily Plan'!$N$4:$N$263,'Daily Plan'!$G$4:$G$263,A23) -> 32 | H23: =SUMIFS('Daily Plan'!$O$4:$O$263,'Daily Plan'!$G$4:$G$263,A23) -> 0 | I23: =IF(SUM($G$5:$G$26)=0,0,G23/SUM($G$5:$G$26)) -> 0.030769231
A24: ART | B24: 3D Medical Artist | C24: 3D Medical Artist | D24: medilens-3d-medical-artist | F24: =COUNTIF('Daily Plan'!$G$4:$G$263,A24) -> 4 | G24: =SUMIFS('Daily Plan'!$N$4:$N$263,'Daily Plan'!$G$4:$G$263,A24) -> 16 | H24: =SUMIFS('Daily Plan'!$O$4:$O$263,'Daily Plan'!$G$4:$G$263,A24) -> 0 | I24: =IF(SUM($G$5:$G$26)=0,0,G24/SUM($G$5:$G$26)) -> 0.015384615
A25: TW | B25: Technical Writer & Localization | C25: Technical Writer & Localization | D25: medilens-technical-writer | F25: =COUNTIF('Daily Plan'!$G$4:$G$263,A25) -> 8 | G25: =SUMIFS('Daily Plan'!$N$4:$N$263,'Daily Plan'!$G$4:$G$263,A25) -> 32 | H25: =SUMIFS('Daily Plan'!$O$4:$O$263,'Daily Plan'!$G$4:$G$263,A25) -> 0 | I25: =IF(SUM($G$5:$G$26)=0,0,G25/SUM($G$5:$G$26)) -> 0.030769231
A26: SUP | B26: Support & Customer Success | C26: Support & Customer Success | D26: medilens-support-success | F26: =COUNTIF('Daily Plan'!$G$4:$G$263,A26) -> 6 | G26: =SUMIFS('Daily Plan'!$N$4:$N$263,'Daily Plan'!$G$4:$G$263,A26) -> 24 | H26: =SUMIFS('Daily Plan'!$O$4:$O$263,'Daily Plan'!$G$4:$G$263,A26) -> 0 | I26: =IF(SUM($G$5:$G$26)=0,0,G26/SUM($G$5:$G$26)) -> 0.023076923
A27: Tổng | F27: =SUM(F5:F26) -> 260 | G27: =SUM(G5:G26) -> 1040 | H27: =SUM(H5:H26) -> 0 | I27: =SUM(I5:I26) -> 1

Sheet Recurring
A1: Việc định kỳ / Recurring work
A2: Không chiếm dòng riêng trong Daily Plan; làm kèm việc chính của ngày. Ngày bắt đầu lấy từ sprint tương ứng.
A3: Tần suất | B3: Cadence | C3: Việc (VI) | D3: Task (EN) | E3: Role | F3: Skill | G3: Bắt đầu từ sprint | H3: Ngày bắt đầu
A4: Hằng ngày | B4: Daily | C4: Daily note 5 phút: hôm qua / hôm nay / vướng mắc | D4: 5-min daily note: yesterday / today / blockers | E4: PM | F4: =IFERROR(INDEX(Roles!$D$5:$D$26,MATCH(E4,Roles!$A$5:$A$26,0)),"") -> medilens-product-manager | G4: S01 | H4: =INDEX(Sprints!$D$4:$D$29,MATCH(G4,Sprints!$A$4:$A$29,0)) -> 46314
A5: Ngày 1 mỗi sprint | B5: Sprint day 1 | C5: Sprint Planning 1 giờ: chọn story, viết Sprint Goal | D5: 1-h Sprint Planning: pick stories, write Sprint Goal | E5: PM | F5: =IFERROR(INDEX(Roles!$D$5:$D$26,MATCH(E5,Roles!$A$5:$A$26,0)),"") -> medilens-product-manager | G5: S01 | H5: =INDEX(Sprints!$D$4:$D$29,MATCH(G5,Sprints!$A$4:$A$29,0)) -> 46314
A6: Ngày 5 mỗi sprint | B6: Sprint day 5 | C6: Backlog refinement 1 giờ cho sprint sau | D6: 1-h backlog refinement for next sprint | E6: BA | F6: =IFERROR(INDEX(Roles!$D$5:$D$26,MATCH(E6,Roles!$A$5:$A$26,0)),"") -> medilens-business-analyst | G6: S01 | H6: =INDEX(Sprints!$D$4:$D$29,MATCH(G6,Sprints!$A$4:$A$29,0)) -> 46314
A7: Ngày 10 mỗi sprint | B7: Sprint day 10 | C7: Review (video ≤ 5 phút) + Retro + cập nhật risk register | D7: Review (≤ 5-min video) + retro + risk register update | E7: PM | F7: =IFERROR(INDEX(Roles!$D$5:$D$26,MATCH(E7,Roles!$A$5:$A$26,0)),"") -> medilens-product-manager | G7: S01 | H7: =INDEX(Sprints!$D$4:$D$29,MATCH(G7,Sprints!$A$4:$A$29,0)) -> 46314
A8: Hằng tuần | B8: Weekly | C8: Xem chi phí AWS và token; xử lý cảnh báo ngân sách | D8: Review AWS and token cost; act on budget alerts | E8: MLO | F8: =IFERROR(INDEX(Roles!$D$5:$D$26,MATCH(E8,Roles!$A$5:$A$26,0)),"") -> medilens-mlops-engineer | G8: S05 | H8: =INDEX(Sprints!$D$4:$D$29,MATCH(G8,Sprints!$A$4:$A$29,0)) -> 46371
A9: Hằng tuần | B9: Weekly | C9: Xem cảnh báo GuardDuty/Security Hub, dependency có CVE | D9: Review GuardDuty/Security Hub findings and CVE dependencies | E9: SEC | F9: =IFERROR(INDEX(Roles!$D$5:$D$26,MATCH(E9,Roles!$A$5:$A$26,0)),"") -> medilens-security-engineer | G9: S03 | H9: =INDEX(Sprints!$D$4:$D$29,MATCH(G9,Sprints!$A$4:$A$29,0)) -> 46342
A10: Hằng tuần | B10: Weekly | C10: Theo dõi drift: loại tài liệu, chất lượng ảnh, tỉ lệ sửa | D10: Drift check: document mix, image quality, correction rate | E10: DE | F10: =IFERROR(INDEX(Roles!$D$5:$D$26,MATCH(E10,Roles!$A$5:$A$26,0)),"") -> medilens-data-engineer | G10: S16 | H10: =INDEX(Sprints!$D$4:$D$29,MATCH(G10,Sprints!$A$4:$A$29,0)) -> 46535
A11: Hằng tháng | B11: Monthly | C11: Báo cáo steering (Done / Next / Rủi ro / Quyết định cần) | D11: Steering report (Done / Next / Risks / Decisions needed) | E11: PM | F11: =IFERROR(INDEX(Roles!$D$5:$D$26,MATCH(E11,Roles!$A$5:$A$26,0)),"") -> medilens-product-manager | G11: S02 | H11: =INDEX(Sprints!$D$4:$D$29,MATCH(G11,Sprints!$A$4:$A$29,0)) -> 46328
A12: Hằng tháng | B12: Monthly | C12: Test khôi phục backup ngẫu nhiên | D12: Random backup restore test | E12: SRE | F12: =IFERROR(INDEX(Roles!$D$5:$D$26,MATCH(E12,Roles!$A$5:$A$26,0)),"") -> medilens-sre-operations | G12: S12 | H12: =INDEX(Sprints!$D$4:$D$29,MATCH(G12,Sprints!$A$4:$A$29,0)) -> 46477
A13: Hằng tháng | B13: Monthly | C13: Patch/upgrade dependency, image nền, Terraform provider | D13: Patch/upgrade dependencies, base images, Terraform providers | E13: OPS | F13: =IFERROR(INDEX(Roles!$D$5:$D$26,MATCH(E13,Roles!$A$5:$A$26,0)),"") -> medilens-cloud-devops-engineer | G13: S06 | H13: =INDEX(Sprints!$D$4:$D$29,MATCH(G13,Sprints!$A$4:$A$29,0)) -> 46385
A14: Hằng tháng | B14: Monthly | C14: Rà soát quyền IAM và truy cập break-glass | D14: Review IAM permissions and break-glass use | E14: SEC | F14: =IFERROR(INDEX(Roles!$D$5:$D$26,MATCH(E14,Roles!$A$5:$A$26,0)),"") -> medilens-security-engineer | G14: S12 | H14: =INDEX(Sprints!$D$4:$D$29,MATCH(G14,Sprints!$A$4:$A$29,0)) -> 46477
A15: Hằng quý | B15: Quarterly | C15: Rà soát License Register | D15: License Register review | E15: DC | F15: =IFERROR(INDEX(Roles!$D$5:$D$26,MATCH(E15,Roles!$A$5:$A$26,0)),"") -> medilens-data-curator | G15: S05 | H15: =INDEX(Sprints!$D$4:$D$29,MATCH(G15,Sprints!$A$4:$A$29,0)) -> 46371
... A23: Hằng năm | B23: Yearly | C23: Rà soát RDR, DPIA, điều khoản | D23: Review RDR, DPIA, terms | E23: REG | F23: =IFERROR(INDEX(Roles!$D$5:$D$26,MATCH(E23,Roles!$A$5:$A$26,0)),"") -> medilens-regulatory-privacy-officer | G23: S02 | H23: =INDEX(Sprints!$D$4:$D$29,MATCH(G23,Sprints!$A$4:$A$29,0)) -> 46328

Sheet Holidays
A1: Ngày nghỉ lễ / Public holidays
A2: Lịch cán bộ, công chức. Thêm/bớt ngày ở các ô vàng (A5:A40); WORKDAY trong Daily Plan dùng vùng này.
A4: Ngày / Date | B4: Tên (VI) | C4: Name (EN) | D4: Nguồn / Source
A5: 46350 | B5: Ngày Văn hóa Việt Nam | C5: Vietnam Culture Day | D5: Nghị quyết 28/2026/QH16, hiệu lực 01/07/2026
A6: 46388 | B6: Tết Dương lịch | C6: New Year's Day | D6: Bộ luật Lao động 2019
A7: 46422 | B7: Tết Nguyên đán (nghỉ 04–10/02/2027) | C7: Lunar New Year break | D7: Thông báo Bộ Nội vụ, áp dụng cán bộ công chức
A8: 46423 | B8: Tết Nguyên đán | C8: Lunar New Year break | D8: Thông báo Bộ Nội vụ
A9: 46426 | B9: Tết Nguyên đán | C9: Lunar New Year break | D9: Thông báo Bộ Nội vụ
A10: 46427 | B10: Tết Nguyên đán | C10: Lunar New Year break | D10: Thông báo Bộ Nội vụ
A11: 46428 | B11: Tết Nguyên đán | C11: Lunar New Year break | D11: Thông báo Bộ Nội vụ
A12: 46493 | B12: Giỗ Tổ Hùng Vương (10/3 âm lịch) | C12: Hung Kings' Commemoration | D12: Lịch âm 2027
A13: 46507 | B13: Ngày Giải phóng miền Nam | C13: Reunification Day | D13: Bộ luật Lao động 2019
A14: 46508 | B14: Quốc tế Lao động (thứ Bảy) | C14: Labour Day (Saturday) | D14: Bộ luật Lao động 2019
A15: 46632 | B15: Quốc khánh | C15: National Day | D15: Bộ luật Lao động 2019
A16: 46633 | B16: Quốc khánh (ngày liền kề) | C16: National Day (adjacent day) | D16: Thông báo Bộ Nội vụ cho 2027

Sheet Change Log
A1: Nhật ký thay đổi baseline / Change log
A2: Ghi mọi thay đổi phạm vi/tiến độ/chi phí trước khi sửa Daily Plan. Dòng 4 là ví dụ định dạng — có thể xóa.
A3: Mã CR | B3: Ngày | C3: Thay đổi | D3: Lý do | E3: Ảnh hưởng phạm vi | F3: Ảnh hưởng tiến độ (ngày) | G3: Ảnh hưởng chi phí (USD) | H3: Sprint bị ảnh hưởng | I3: Người duyệt (role) | J3: Trạng thái
A4: CR-000 (ví dụ) | B4: 46359 | C4: Dời 'Hướng dẫn chụp bệnh án' từ S06 sang S07 | D4: Ưu tiên sửa OCR cho ảnh điện thoại | E4: Không đổi | F4: 1 | G4: 0 | H4: S06, S07 | I4: PM | J4: Ví dụ
